Módulo 2 - Ejercicios/ejercicio_5/pipeline_3stage.v
`timescale 1ns/1ps

module pipeline_3stage (
    input  logic               clk,
    input  logic               rst_n,           // Reset asíncrono activo-bajo.
    input  logic signed [7:0]  x_in,            // Interfaz de entrada (Slave AXI-Stream).
    input  logic               valid_in,
    output logic               ready_out,
    output logic signed [15:0] y_out,           // Interfaz de salida (Master AXI-Stream).
    output logic               valid_out,
    input  logic               ready_in
);

    // Parámetros/Constantes del cálculo: A=5, B=3 (con signo).
    localparam logic signed [7:0] A = 8'sd5;
    localparam logic signed [7:0] B = 8'sd3;

    // Habilitador global del pipeline (Back-pressure).
    logic pipe_en;
    assign pipe_en   = ready_in; 
    assign ready_out = ready_in;                // Propagación directa de back-pressure.

    // Registros intermedios para datos (Data Pipeline)
    logic signed [8:0]  stg1_data;              // 9 bits para evitar overflow en la suma.
    logic signed [15:0] stg2_data;              // Resultado del producto.
    logic signed [15:0] stg3_data;              // Resultado del shift aritmético.

    // Registros intermedios para validez (Valid Pipeline):
    logic stg1_valid;
    logic stg2_valid;
    logic stg3_valid;

    // Lógica secuencial del Pipeline:
    always_ff @(posedge clk or negedge rst_n) begin
        if (!rst_n) begin
            stg1_valid <= 1'b0;
            stg2_valid <= 1'b0;
            stg3_valid <= 1'b0;
            stg1_data  <= '0;
            stg2_data  <= '0;
            stg3_data  <= '0;
        end 
        else if (pipe_en) begin
            // Etapa 1: Suma x + A (se expande a 9 bits firmados).
            stg1_data  <= $signed(x_in) + $signed(A);
            stg1_valid <= valid_in;

            // Etapa 2: Multiplicación por B.
            stg2_data  <= stg1_data * $signed(B);
            stg2_valid <= stg1_valid;

            // Etapa 3: Shift derecho aritmético >>> 4.
            stg3_data  <= stg2_data >>> 4;
            stg3_valid <= stg2_valid;
        end
    end

    // Asignación continua a las salidas:
    assign y_out     = stg3_data;
    assign valid_out = stg3_valid;
endmodule

Módulo 2 - Ejercicios/ejercicio_5/tb_pipeline.v
`timescale 1ns / 1ps

module tb_pipeline;

    // Señales
    logic               clk;
    logic               rst_n;
    logic signed [7:0]  x_in;
    logic               valid_in;
    logic               ready_out;
    logic signed [15:0] y_out;
    logic               valid_out;
    logic               ready_in;

    // Instancia del DUT
    pipeline_3stage dut (
        .clk(clk),
        .rst_n(rst_n),
        .x_in(x_in),
        .valid_in(valid_in),
        .ready_out(ready_out),
        .y_out(y_out),
        .valid_out(valid_out),
        .ready_in(ready_in)
    );

    // Generación de Clock (100 MHz)
    initial begin
        clk = 0;
        forever #5 clk = ~clk;
    end

    // =========================================================================
    // GOLDEN MODEL EN SOFTWARE Y AUTO-CHECKER
    // =========================================================================
    
    // Cola para guardar los resultados esperados (FIFO)
    logic signed [15:0] expected_queue [$];

    // Función del Golden Model matemático
    function automatic logic signed [15:0] golden_model(input logic signed [7:0] x);
        logic signed [15:0] y;
        // y = ((x + 5) * 3) >>> 4
        y = ((x + 8'sd5) * 8'sd3) >>> 4; 
        return y;
    endfunction

    // Monitor de Entrada: Usa 'always' normal para evitar warnings de síntesis
    always @(posedge clk) begin
        if (valid_in && ready_out && rst_n) begin
            expected_queue.push_back(golden_model(x_in));
        end
    end

    // Monitor de Salida: Compara el DUT vs el Golden Model
    integer errors = 0;
    always @(posedge clk) begin
        if (valid_out && ready_in && rst_n) begin
            logic signed [15:0] exp_val;
            exp_val = expected_queue.pop_front();
            
            if (y_out !== exp_val) begin
                $display("ERROR en t=%0t: x_in=%d | Esperado=%d | Obtenido=%d", $time, x_in, exp_val, y_out);
                errors++;
            end
        end
    end

    // =========================================================================
    // MEDICIÓN DE THROUGHPUT
    // =========================================================================
    integer total_cycles = 0;
    integer valid_transfers = 0;
    logic   measure_en = 0;

    always @(posedge clk) begin
        if (measure_en) total_cycles++;
        if (valid_out && ready_in && rst_n && measure_en) valid_transfers++;
    end

    // =========================================================================
    // BLOQUE DE ESTÍMULOS
    // =========================================================================
    initial begin
        $dumpfile("pipeline.vcd");
        $dumpvars(0, tb_pipeline);

        // Inicialización
        rst_n    = 0;
        valid_in = 0;
        ready_in = 1;
        x_in     = 0;
        
        #20 rst_n = 1; // Liberar reset
        @(posedge clk);

        // ---------------------------------------------------------
        // FASE 1: Régimen sin stalls (ready_in = 1 siempre)
        // ---------------------------------------------------------
        $display(">>> INICIANDO FASE 1: Transmision sin stalls...");
        measure_en = 1;
        
        repeat(20) begin
            valid_in <= 1;
            // Generar un número aleatorio entre -128 y 127
            x_in <= $random; 
            @(posedge clk);
        end

        valid_in <= 0;
        // Esperar a que el pipeline se vacíe (flushing)
        repeat(5) @(posedge clk); 
        
        measure_en = 0;
        $display("Rendimiento Fase 1 (Ideal): %0d muestras en %0d ciclos.", valid_transfers, total_cycles);

        // ---------------------------------------------------------
        // FASE 2: Probar con stall alternando (ready_in = random)
        // ---------------------------------------------------------
        $display(">>> INICIANDO FASE 2: Transmision con STALLS...");
        total_cycles = 0;
        valid_transfers = 0;
        measure_en = 1;

        repeat(50) begin
            // ready_in alterna pseudo-aleatoriamente para forzar stalls
            ready_in <= $random; 
            valid_in <= $random;
            if (valid_in && ready_out) begin
                x_in <= $random;
            end
            @(posedge clk);
        end

        // Limpiar pipeline al finalizar
        valid_in <= 0;
        ready_in <= 1;
        repeat(10) @(posedge clk);
        measure_en = 0;

        $display("Rendimiento Fase 2 (Con Stalls): %0d muestras en %0d ciclos.", valid_transfers, total_cycles);

        // ---------------------------------------------------------
        // REPORTE FINAL
        // ---------------------------------------------------------
        $display("");
        $display("==================================================");
        $display("   RESULTADOS DE LA SIMULACIÓN - PIPELINE AXI-S   ");
        $display("==================================================");
        if (errors == 0 && expected_queue.size() == 0) begin
            $display("ESTADO: [ PASS ] - El pipeline funciona perfecto.");
        end else begin
            $display("ESTADO: [ FAIL ] - Se encontraron %0d errores.", errors);
        end
        $display("Throughput ideal teorico: 1.0 muestras/ciclo");
        $display("==================================================");
        $display("");
        
        $finish;
    end

endmodule

Módulo 2 - Ejercicios/ejercicio_5/pipeline.vcd
$date
	Thu Aug  6 09:57:11 2026
$end
$version
	Icarus Verilog
$end
$timescale
	1ps
$end
$scope module tb_pipeline $end
$var wire 16 ! y_out [15:0] $end
$var wire 1 " valid_out $end
$var wire 1 # ready_out $end
$var reg 1 $ clk $end
$var reg 1 % measure_en $end
$var reg 1 & ready_in $end
$var reg 1 ' rst_n $end
$var reg 1 ( valid_in $end
$var reg 8 ) x_in [7:0] $end
$var integer 32 * errors [31:0] $end
$var integer 32 + total_cycles [31:0] $end
$var integer 32 , valid_transfers [31:0] $end
$scope function golden_model $end
$upscope $end
$scope module dut $end
$var wire 1 $ clk $end
$var wire 1 - pipe_en $end
$var wire 1 & ready_in $end
$var wire 1 # ready_out $end
$var wire 1 ' rst_n $end
$var wire 1 ( valid_in $end
$var wire 1 " valid_out $end
$var wire 8 . x_in [7:0] $end
$var wire 16 / y_out [15:0] $end
$var parameter 8 0 A $end
$var parameter 8 1 B $end
$var reg 9 2 stg1_data [8:0] $end
$var reg 1 3 stg1_valid $end
$var reg 16 4 stg2_data [15:0] $end
$var reg 1 5 stg2_valid $end
$var reg 16 6 stg3_data [15:0] $end
$var reg 1 7 stg3_valid $end
$upscope $end
$scope begin $unm_blk_8 $end
$var reg 16 8 exp_val [15:0] $end
$upscope $end
$upscope $end
$enddefinitions $end
$comment Show the parameter values. $end
$dumpall
b11 1
b101 0
$end
#0
$dumpvars
bx 8
07
b0 6
05
b0 4
03
b0 2
b0 /
b0 .
1-
b0 ,
b0 +
b0 *
b0 )
0(
0'
1&
0%
0$
1#
0"
b0 !
$end
#5000
1$
#10000
0$
#15000
1$
#20000
0$
1'
#25000
b101 2
b100100 )
b100100 .
1(
b1 +
1%
1$
#30000
0$
#35000
b1111 4
13
b101001 2
b10000001 )
b10000001 .
b10 +
1$
#40000
0$
#45000
15
b1111011 4
b110000110 2
b1001 )
b1001 .
b11 +
1$
#50000
0$
#55000
1"
17
b111 !
b111 /
b111 6
b1111111010010010 4
b1110 2
b1100011 )
b1100011 .
b100 +
1$
#60000
0$
#65000
b1111111111101001 !
b1111111111101001 /
b1111111111101001 6
b101010 4
b1101000 2
b1101 )
b1101 .
b111 8
b1 ,
b101 +
1$
#70000
0$
#75000
b10 !
b10 /
b10 6
b100111000 4
b10010 2
b10001101 )
b10001101 .
b1111111111101001 8
b10 ,
b110 +
1$
#80000
0$
#85000
b10011 !
b10011 /
b10011 6
b110110 4
b110010010 2
b1100101 )
b1100101 .
b10 8
b11 ,
b111 +
1$
#90000
0$
#95000
b11 !
b11 /
b11 6
b1111111010110110 4
b1101010 2
b10010 )
b10010 .
b10011 8
b100 ,
b1000 +
1$
#100000
0$
#105000
b1111111111101011 !
b1111111111101011 /
b1111111111101011 6
b100111110 4
b10111 2
b1 )
b1 .
b11 8
b101 ,
b1001 +
1$
#110000
0$
#115000
b10011 !
b10011 /
b10011 6
b1000101 4
b110 2
b1101 )
b1101 .
b1111111111101011 8
b110 ,
b1010 +
1$
#120000
0$
#125000
b100 !
b100 /
b100 6
b10010 4
b10010 2
b1110110 )
b1110110 .
b10011 8
b111 ,
b1011 +
1$
#130000
0$
#135000
b1 !
b1 /
b1 6
b110110 4
b1111011 2
b111101 )
b111101 .
b100 8
b1000 ,
b1100 +
1$
#140000
0$
#145000
b11 !
b11 /
b11 6
b101110001 4
b1000010 2
b11101101 )
b11101101 .
b1 8
b1001 ,
b1101 +
1$
#150000
0$
#155000
b10111 !
b10111 /
b10111 6
b11000110 4
b111110010 2
b10001100 )
b10001100 .
b11 8
b1010 ,
b1110 +
1$
#160000
0$
#165000
b1100 !
b1100 /
b1100 6
b1111111111010110 4
b110010001 2
b11111001 )
b11111001 .
b10111 8
b1011 ,
b1111 +
1$
#170000
0$
#175000
b1111111111111101 !
b1111111111111101 /
b1111111111111101 6
b1111111010110011 4
b111111110 2
b11000110 )
b11000110 .
b1100 8
b1100 ,
b10000 +
1$
#180000
0$
#185000
b1111111111101011 !
b1111111111101011 /
b1111111111101011 6
b1111111111111010 4
b111001011 2
b11000101 )
b11000101 .
b1111111111111101 8
b1101 ,
b10001 +
1$
#190000
0$
#195000
b1111111111111111 !
b1111111111111111 /
b1111111111111111 6
b1111111101100001 4
b111001010 2
b10101010 )
b10101010 .
b1111111111101011 8
b1110 ,
b10010 +
1$
#200000
0$
#205000
b1111111111110110 !
b1111111111110110 /
b1111111111110110 6
b1111111101011110 4
b110101111 2
b11100101 )
b11100101 .
b1111111111111111 8
b1111 ,
b10011 +
1$
#210000
0$
#215000
b1111111111110101 !
b1111111111110101 /
b1111111111110101 6
b1111111100001101 4
b111101010 2
b1110111 )
b1110111 .
b1111111111110110 8
b10000 ,
b10100 +
1$
#220000
0$
#225000
b1111111111110000 !
b1111111111110000 /
b1111111111110000 6
b1111111110111110 4
b1111100 2
0(
b1111111111110101 8
b10001 ,
b10101 +
1$
#230000
0$
#235000
b1111111111111011 !
b1111111111111011 /
b1111111111111011 6
b101110100 4
03
b1111111111110000 8
b10010 ,
b10110 +
1$
#240000
0$
#245000
b10111 !
b10111 /
b10111 6
05
b1111111111111011 8
b10011 ,
b10111 +
1$
#250000
0$
#255000
0"
07
b10111 8
b10100 ,
b11000 +
1$
#260000
0$
#265000
b11001 +
1$
#270000
0$
#275000
1(
0-
0#
0&
b0 ,
1%
b0 +
1$
#280000
0$
#285000
0(
b1 +
1$
#290000
0$
#295000
1(
b10 +
1$
#300000
0$
#305000
b11 +
1$
#310000
0$
#315000
1-
1#
1&
b100 +
1$
#320000
0$
#325000
13
b10000000 )
b10000000 .
0(
b101 +
1$
#330000
0$
#335000
15
03
b110000101 2
0-
0#
0&
b110 +
1$
#340000
0$
#345000
1-
1#
1&
b111 +
1$
#350000
0$
#355000
1"
17
05
b1111111010001111 4
1(
b1000 +
1$
#360000
0$
#365000
0"
07
b1111111111101000 !
b1111111111101000 /
b1111111111101000 6
13
b11010101 )
b11010101 .
b1 ,
b1001 +
1$
#370000
0$
#375000
15
b111011010 2
b11101 )
b11101 .
0(
0-
0#
0&
b1010 +
1$
#380000
0$
#385000
1(
1-
1#
1&
b1011 +
1$
#390000
0$
#395000
1"
17
b1111111110001110 4
b100010 2
b111100 )
b111100 .
0(
0-
0#
0&
b1100 +
1$
#400000
0$
#405000
b1101 +
1$
#410000
0$
#415000
1-
1#
1&
b1110 +
1$
#420000
0$
#425000
b1111111111111000 !
b1111111111111000 /
b1111111111111000 6
b1100110 4
03
b1000001 2
1(
0-
0#
0&
b1111111111101000 8
b10 ,
b1111 +
1$
#430000
0$
#435000
0(
1-
1#
1&
b10000 +
1$
#440000
0$
#445000
b110 !
b110 /
b110 6
05
b11000011 4
0-
0#
0&
b1111111111111000 8
b11 ,
b10001 +
1$
#450000
0$
#455000
b10010 +
1$
#460000
0$
#465000
1(
1-
1#
1&
b10011 +
1$
#470000
0$
#475000
0"
07
b1100 !
b1100 /
b1100 6
13
b111011 )
b111011 .
b110 8
b100 ,
b10100 +
1$
#480000
0$
#485000
15
b1000000 2
b10101 )
b10101 .
0(
0-
0#
0&
b10101 +
1$
#490000
0$
#495000
1(
1-
1#
1&
b10110 +
1$
#500000
0$
#505000
1"
17
b11000000 4
b11010 2
b10011111 )
b10011111 .
0(
0-
0#
0&
b10111 +
1$
#510000
0$
#515000
1-
1#
1&
b11000 +
1$
#520000
0$
#525000
b1001110 4
03
b110100100 2
1(
b1100 8
b101 ,
b11001 +
1$
#530000
0$
#535000
b100 !
b100 /
b100 6
05
b1111111011101100 4
13
b10001001 )
b10001001 .
0-
0#
0&
b110 ,
b11010 +
1$
#540000
0$
#545000
0(
1-
1#
1&
b11011 +
1$
#550000
0$
#555000
0"
07
b1111111111101110 !
b1111111111101110 /
b1111111111101110 6
15
03
b110001110 2
1(
b100 8
b111 ,
b11100 +
1$
#560000
0$
#565000
1"
17
05
b1111111010101010 4
13
b11000010 )
b11000010 .
0(
0-
0#
0&
b11101 +
1$
#570000
0$
#575000
1(
b11110 +
1$
#580000
0$
#585000
0(
1-
1#
1&
b11111 +
1$
#590000
0$
#595000
0"
07
b1111111111101010 !
b1111111111101010 /
b1111111111101010 6
15
03
b111000111 2
1(
0-
0#
0&
b1111111111101110 8
b1000 ,
b100000 +
1$
#600000
0$
#605000
1-
1#
1&
b100001 +
1$
#610000
0$
#615000
1"
17
05
b1111111101010101 4
13
b1111000 )
b1111000 .
b100010 +
1$
#620000
0$
#625000
0"
07
b1111111111110101 !
b1111111111110101 /
b1111111111110101 6
15
b1111101 2
b111111 )
b111111 .
b1111111111101010 8
b1001 ,
b100011 +
1$
#630000
0$
#635000
1"
17
b101110111 4
b1000100 2
b10000110 )
b10000110 .
0(
0-
0#
0&
b100100 +
1$
#640000
0$
#645000
b100101 +
1$
#650000
0$
#655000
b100110 +
1$
#660000
0$
#665000
1(
1-
1#
1&
b100111 +
1$
#670000
0$
#675000
b10111 !
b10111 /
b10111 6
b11001100 4
b110001011 2
b1011111 )
b1011111 .
b1111111111110101 8
b1010 ,
b101000 +
1$
#680000
0$
#685000
b1100 !
b1100 /
b1100 6
b1111111010100001 4
b1100100 2
b11001011 )
b11001011 .
0-
0#
0&
b10111 8
b1011 ,
b101001 +
1$
#690000
0$
#695000
0(
b101010 +
1$
#700000
0$
#705000
1(
1-
1#
1&
b101011 +
1$
#710000
0$
#715000
b1111111111101010 !
b1111111111101010 /
b1111111111101010 6
b100101100 4
b111010000 2
b10110101 )
b10110101 .
0-
0#
0&
b1100 8
b1100 ,
b101100 +
1$
#720000
0$
#725000
1-
1#
1&
b101101 +
1$
#730000
0$
#735000
b10010 !
b10010 /
b10010 6
b1111111101110000 4
b110111010 2
b101010 )
b101010 .
0(
0-
0#
0&
b1111111111101010 8
b1101 ,
b101110 +
1$
#740000
0$
#745000
1-
1#
1&
b101111 +
1$
#750000
0$
#755000
b1111111111110111 !
b1111111111110111 /
b1111111111110111 6
b1111111100101110 4
03
b101111 2
0-
0#
0&
b10010 8
b1110 ,
b110000 +
1$
#760000
0$
#765000
1(
1-
1#
1&
b110001 +
1$
#770000
0$
#775000
b1111111111110010 !
b1111111111110010 /
b1111111111110010 6
05
b10001101 4
13
0(
b1111111111110111 8
b1111 ,
b110010 +
1$
#780000
0$
#785000
0"
07
b1000 !
b1000 /
b1000 6
15
03
b1111111111110010 8
b10000 ,
b110011 +
1$
#790000
0$
#795000
1"
17
05
b110100 +
1$
#800000
0$
#805000
0"
07
b1000 8
b10001 ,
b110101 +
1$
#810000
0$
#815000
b110110 +
1$
#820000
0$
#825000
b110111 +
1$
#830000
0$
#835000
b111000 +
1$
#840000
0$
#845000
b111001 +
1$
#850000
0$
#855000
b111010 +
1$
#860000
0$
#865000
b111011 +
1$
#870000
0$
#875000
0%
b111100 +
1$
