Módulo 2 - Ejercicios/ejercicio_3/bcd_counter.v
`timescale 1ns/1ps

module bcd_counter (
    input  logic       clk,
    input  logic       rst,         // Reset síncrono activo-alto
    input  logic       en,          // Enable
    output logic [3:0] cnt,         // Salida de cuenta (4 bits)
    output logic       tc           // Terminal count (1 bit)
);

    // Lógica secuencial: Contador BCD
    always_ff @(posedge clk) begin
        if (rst) begin
            cnt <= 4'd0;            // Reset síncrono activo-alto.
        end
        else if (en) begin
            if (cnt == 4'd9) begin
                cnt <= 4'd0;        // Rollover al llegar a 9.
            end 
            else begin
                cnt <= cnt + 1'b1;  // Incremento normal.
            end
        end
    end

    // Lógica combinacional: Pulso de fin de cuenta
    // Se asigna directamente como pidió el profe para evitar el desfase de 1 ciclo
    assign tc = (cnt == 4'd9) && en;
endmodule

Módulo 2 - Ejercicios/ejercicio_3/tb_bcd_counter.v
`timescale 1ns/1ps

module tb_bcd_counter;
    // Declaración de señales
    logic       clk;
    logic       rst;
    logic       en;
    logic [3:0] cnt;
    logic       tc;

    integer tc_count;                   // Variable interna del testbench para el auto-check:

    bcd_counter dut (                   // Instancia del módulo (Device Under Test):
        .clk(clk),
        .rst(rst),
        .en(en),
        .cnt(cnt),
        .tc(tc)
    );
    
    initial begin                       // Generación de Clock a 100 MHz (Periodo de 10 ns -> cambia cada 5 ns)
        clk = 0;
        forever #5 clk = ~clk;
    end

    // Lógica del Golden Model / Auto-Checker:
    //  - Detecta y cuenta los pulsos de 'tc' en cada flanco de subida
    always_ff @(posedge clk) begin
        if (rst) begin
            tc_count <= 0;
        end
        else if (tc && en) begin
            tc_count <= tc_count + 1;
        end
    end

    // Bloque principal de estímulos
    initial begin
        // Generación del archivo VCD para GTKWave:
        $dumpfile("bcd_counter.vcd");
        $dumpvars(0, tb_bcd_counter);

        // 1. Inicialización y Reset Síncrono:
        rst = 1;
        en  = 0;
        
        // Esperamos un par de flancos para que el reset síncrono haga efecto:
        @(posedge clk);
        @(posedge clk);
        
        // 2. Liberamos el reset y activamos el enable:
        rst = 0;
        en  = 1;

        // 3. Ejecutamos exactamente 100 ciclos de reloj con el contador habilitado:
        repeat (100) @(posedge clk);

        // 4. Pausamos el contador:
        en = 0;
        @(posedge clk);

        // 5. Verificación automática (Auto-check):
        $display("");
        $display("==================================================");
        $display("   RESULTADOS DE LA SIMULACIÓN - BCD COUNTER      ");
        $display("==================================================");
        $display("Ciclos con EN=1 ejecutados: 100");
        $display("Pulsos 'tc' detectados:     %0d", tc_count);
        $display("--------------------------------------------------");
        
        if (tc_count == 10) begin
            $display("ESTADO: [ PASS ] - El rollover funciono perfecto.");
        end else begin
            $display("ESTADO: [ FAIL ] - Hubo un error en la cuenta.");
        end
        $display("==================================================");
        $display("");

        // Fin de la simulación:
        $finish;
    end
endmodule

Módulo 2 - Ejercicios/ejercicio_3/bcd_counter.vcd
$date
	Thu Aug  6 07:12:16 2026
$end
$version
	Icarus Verilog
$end
$timescale
	1ps
$end
$scope module tb_bcd_counter $end
$var wire 1 ! tc $end
$var wire 4 " cnt [3:0] $end
$var reg 1 # clk $end
$var reg 1 $ en $end
$var reg 1 % rst $end
$var integer 32 & tc_count [31:0] $end
$scope module dut $end
$var wire 1 # clk $end
$var wire 1 $ en $end
$var wire 1 % rst $end
$var wire 1 ! tc $end
$var reg 4 ' cnt [3:0] $end
$upscope $end
$upscope $end
$enddefinitions $end
$comment Show the parameter values. $end
$dumpall
$end
#0
$dumpvars
bx '
bx &
1%
0$
0#
bx "
0!
$end
#5000
b0 "
b0 '
b0 &
1#
#10000
0#
#15000
1$
0%
1#
#20000
0#
#25000
b1 "
b1 '
1#
#30000
0#
#35000
b10 "
b10 '
1#
#40000
0#
#45000
b11 "
b11 '
1#
#50000
0#
#55000
b100 "
b100 '
1#
#60000
0#
#65000
b101 "
b101 '
1#
#70000
0#
#75000
b110 "
b110 '
1#
#80000
0#
#85000
b111 "
b111 '
1#
#90000
0#
#95000
b1000 "
b1000 '
1#
#100000
0#
#105000
1!
b1001 "
b1001 '
1#
#110000
0#
#115000
0!
b1 &
b0 "
b0 '
1#
#120000
0#
#125000
b1 "
b1 '
1#
#130000
0#
#135000
b10 "
b10 '
1#
#140000
0#
#145000
b11 "
b11 '
1#
#150000
0#
#155000
b100 "
b100 '
1#
#160000
0#
#165000
b101 "
b101 '
1#
#170000
0#
#175000
b110 "
b110 '
1#
#180000
0#
#185000
b111 "
b111 '
1#
#190000
0#
#195000
b1000 "
b1000 '
1#
#200000
0#
#205000
1!
b1001 "
b1001 '
1#
#210000
0#
#215000
0!
b10 &
b0 "
b0 '
1#
#220000
0#
#225000
b1 "
b1 '
1#
#230000
0#
#235000
b10 "
b10 '
1#
#240000
0#
#245000
b11 "
b11 '
1#
#250000
0#
#255000
b100 "
b100 '
1#
#260000
0#
#265000
b101 "
b101 '
1#
#270000
0#
#275000
b110 "
b110 '
1#
#280000
0#
#285000
b111 "
b111 '
1#
#290000
0#
#295000
b1000 "
b1000 '
1#
#300000
0#
#305000
1!
b1001 "
b1001 '
1#
#310000
0#
#315000
0!
b11 &
b0 "
b0 '
1#
#320000
0#
#325000
b1 "
b1 '
1#
#330000
0#
#335000
b10 "
b10 '
1#
#340000
0#
#345000
b11 "
b11 '
1#
#350000
0#
#355000
b100 "
b100 '
1#
#360000
0#
#365000
b101 "
b101 '
1#
#370000
0#
#375000
b110 "
b110 '
1#
#380000
0#
#385000
b111 "
b111 '
1#
#390000
0#
#395000
b1000 "
b1000 '
1#
#400000
0#
#405000
1!
b1001 "
b1001 '
1#
#410000
0#
#415000
0!
b100 &
b0 "
b0 '
1#
#420000
0#
#425000
b1 "
b1 '
1#
#430000
0#
#435000
b10 "
b10 '
1#
#440000
0#
#445000
b11 "
b11 '
1#
#450000
0#
#455000
b100 "
b100 '
1#
#460000
0#
#465000
b101 "
b101 '
1#
#470000
0#
#475000
b110 "
b110 '
1#
#480000
0#
#485000
b111 "
b111 '
1#
#490000
0#
#495000
b1000 "
b1000 '
1#
#500000
0#
#505000
1!
b1001 "
b1001 '
1#
#510000
0#
#515000
0!
b101 &
b0 "
b0 '
1#
#520000
0#
#525000
b1 "
b1 '
1#
#530000
0#
#535000
b10 "
b10 '
1#
#540000
0#
#545000
b11 "
b11 '
1#
#550000
0#
#555000
b100 "
b100 '
1#
#560000
0#
#565000
b101 "
b101 '
1#
#570000
0#
#575000
b110 "
b110 '
1#
#580000
0#
#585000
b111 "
b111 '
1#
#590000
0#
#595000
b1000 "
b1000 '
1#
#600000
0#
#605000
1!
b1001 "
b1001 '
1#
#610000
0#
#615000
0!
b110 &
b0 "
b0 '
1#
#620000
0#
#625000
b1 "
b1 '
1#
#630000
0#
#635000
b10 "
b10 '
1#
#640000
0#
#645000
b11 "
b11 '
1#
#650000
0#
#655000
b100 "
b100 '
1#
#660000
0#
#665000
b101 "
b101 '
1#
#670000
0#
#675000
b110 "
b110 '
1#
#680000
0#
#685000
b111 "
b111 '
1#
#690000
0#
#695000
b1000 "
b1000 '
1#
#700000
0#
#705000
1!
b1001 "
b1001 '
1#
#710000
0#
#715000
0!
b111 &
b0 "
b0 '
1#
#720000
0#
#725000
b1 "
b1 '
1#
#730000
0#
#735000
b10 "
b10 '
1#
#740000
0#
#745000
b11 "
b11 '
1#
#750000
0#
#755000
b100 "
b100 '
1#
#760000
0#
#765000
b101 "
b101 '
1#
#770000
0#
#775000
b110 "
b110 '
1#
#780000
0#
#785000
b111 "
b111 '
1#
#790000
0#
#795000
b1000 "
b1000 '
1#
#800000
0#
#805000
1!
b1001 "
b1001 '
1#
#810000
0#
#815000
0!
b1000 &
b0 "
b0 '
1#
#820000
0#
#825000
b1 "
b1 '
1#
#830000
0#
#835000
b10 "
b10 '
1#
#840000
0#
#845000
b11 "
b11 '
1#
#850000
0#
#855000
b100 "
b100 '
1#
#860000
0#
#865000
b101 "
b101 '
1#
#870000
0#
#875000
b110 "
b110 '
1#
#880000
0#
#885000
b111 "
b111 '
1#
#890000
0#
#895000
b1000 "
b1000 '
1#
#900000
0#
#905000
1!
b1001 "
b1001 '
1#
#910000
0#
#915000
0!
b1001 &
b0 "
b0 '
1#
#920000
0#
#925000
b1 "
b1 '
1#
#930000
0#
#935000
b10 "
b10 '
1#
#940000
0#
#945000
b11 "
b11 '
1#
#950000
0#
#955000
b100 "
b100 '
1#
#960000
0#
#965000
b101 "
b101 '
1#
#970000
0#
#975000
b110 "
b110 '
1#
#980000
0#
#985000
b111 "
b111 '
1#
#990000
0#
#995000
b1000 "
b1000 '
1#
#1000000
0#
#1005000
1!
b1001 "
b1001 '
1#
#1010000
0#
#1015000
b1010 &
b0 "
b0 '
0!
0$
1#
