Módulo 4 - Ejercicios/ejercicio_1/full_adder.sv
`timescale 1ns/1ps

module full_adder (
    input  logic a,
    input  logic b,
    input  logic cin,
    output logic s,
    output logic cout
);
    assign {cout, s} = a + b + cin;
endmodule

Módulo 4 - Ejercicios/ejercicio_1/rca.sv
`timescale 1ns/1ps

module rca #(
    parameter N = 8
) (
    input  logic [N-1:0] a,
    input  logic [N-1:0] b,
    input  logic         cin,
    output logic [N-1:0] s,
    output logic         cout
);
    logic [N:0] c;
    assign c[0] = cin;

    genvar i;
    generate 
        for (i = 0; i < N; i = i + 1) begin : fa_chain
            full_adder u_fa (
                .a   (a[i]),
                .b   (b[i]),
                .cin (c[i]),
                .s   (s[i]),
                .cout(c[i+1])
            );
        end
    endgenerate

    assign cout = c[N];
endmodule

Módulo 4 - Ejercicios/ejercicio_1/tb_rca.sv
`timescale 1ns/1ps

module tb_rca;
    localparam N = 8;

    logic [N-1:0] a, b, s;
    logic         cin, cout;
    logic [N:0]   expected;
    int           errors = 0;

    rca #(
        .N(N)
    ) dut (
        .a   (a),
        .b   (b),
        .cin (cin),
        .s   (s),
        .cout(cout)
    );

    task check_result(input string name);
        expected = a + b + cin;
        if ({cout, s} !== expected) begin
            $display("[FAIL] %s: a=%d, b=%d, cin=%b | Obtenido: {cout=%b, s=%d}, Esperado: %d", 
                     name, a, b, cin, cout, s, expected);
            errors++;
        end
    endtask

    initial begin
        $dumpfile("rca.vcd");
        $dumpvars(0, tb_rca);

        // 1. Borde inferior: 0 + 0
        a = 0; b = 0; cin = 0; #10;
        check_result("Borde Inferior");

        // 2. Borde superior: max + max
        a = '1; b = '1; cin = 0; #10;
        check_result("Borde Superior");

        // 3. Caso con Carry-out = 1
        a = 8'hFF; b = 8'h01; cin = 0; #10;
        check_result("Carry-out en 1");

        // 4. 500 casos aleatorios
        for (int i = 0; i < 500; i++) begin
            a   = $urandom;
            b   = $urandom;
            cin = $urandom_range(0, 1);
            #10;
            check_result("Random");
        end

        // Reporte final en consola
        if (errors == 0) begin
            $display("=========================================");
            $display("PASS: Todos los casos evaluados con exito.");
            $display("=========================================");
        end else begin
            $display("=========================================");
            $display("FAIL: Se encontraron %0d errores.", errors);
            $display("=========================================");
        end

        $finish;
    end
endmodule

Módulo 4 - Ejercicios/ejercicio_1/rca.vcd
$date
	Wed Aug 26 13:45:47 2026
$end
$version
	Icarus Verilog
$end
$timescale
	1ps
$end
$scope module tb_rca $end
$var wire 8 ! s [7:0] $end
$var wire 1 " cout $end
$var parameter 32 # N $end
$var reg 8 $ a [7:0] $end
$var reg 8 % b [7:0] $end
$var reg 1 & cin $end
$var reg 9 ' expected [8:0] $end
$var integer 32 ( errors [31:0] $end
$scope module dut $end
$var wire 8 ) a [7:0] $end
$var wire 8 * b [7:0] $end
$var wire 1 & cin $end
$var wire 8 + s [7:0] $end
$var wire 1 " cout $end
$var wire 9 , c [8:0] $end
$var parameter 32 - N $end
$scope begin fa_chain[0] $end
$var parameter 2 . i $end
$scope module u_fa $end
$var wire 1 / a $end
$var wire 1 0 b $end
$var wire 1 1 cin $end
$var wire 1 2 s $end
$var wire 1 3 cout $end
$upscope $end
$upscope $end
$scope begin fa_chain[1] $end
$var parameter 2 4 i $end
$scope module u_fa $end
$var wire 1 5 a $end
$var wire 1 6 b $end
$var wire 1 7 cin $end
$var wire 1 8 s $end
$var wire 1 9 cout $end
$upscope $end
$upscope $end
$scope begin fa_chain[2] $end
$var parameter 3 : i $end
$scope module u_fa $end
$var wire 1 ; a $end
$var wire 1 < b $end
$var wire 1 = cin $end
$var wire 1 > s $end
$var wire 1 ? cout $end
$upscope $end
$upscope $end
$scope begin fa_chain[3] $end
$var parameter 3 @ i $end
$scope module u_fa $end
$var wire 1 A a $end
$var wire 1 B b $end
$var wire 1 C cin $end
$var wire 1 D s $end
$var wire 1 E cout $end
$upscope $end
$upscope $end
$scope begin fa_chain[4] $end
$var parameter 4 F i $end
$scope module u_fa $end
$var wire 1 G a $end
$var wire 1 H b $end
$var wire 1 I cin $end
$var wire 1 J s $end
$var wire 1 K cout $end
$upscope $end
$upscope $end
$scope begin fa_chain[5] $end
$var parameter 4 L i $end
$scope module u_fa $end
$var wire 1 M a $end
$var wire 1 N b $end
$var wire 1 O cin $end
$var wire 1 P s $end
$var wire 1 Q cout $end
$upscope $end
$upscope $end
$scope begin fa_chain[6] $end
$var parameter 4 R i $end
$scope module u_fa $end
$var wire 1 S a $end
$var wire 1 T b $end
$var wire 1 U cin $end
$var wire 1 V s $end
$var wire 1 W cout $end
$upscope $end
$upscope $end
$scope begin fa_chain[7] $end
$var parameter 4 X i $end
$scope module u_fa $end
$var wire 1 Y a $end
$var wire 1 Z b $end
$var wire 1 [ cin $end
$var wire 1 \ s $end
$var wire 1 ] cout $end
$upscope $end
$upscope $end
$upscope $end
$scope begin $ivl_for_loop0 $end
$var integer 32 ^ i [31:0] $end
$upscope $end
$scope task check_result $end
$upscope $end
$upscope $end
$enddefinitions $end
$comment Show the parameter values. $end
$dumpall
b111 X
b110 R
b101 L
b100 F
b11 @
b10 :
b1 4
b0 .
b1000 -
b1000 #
$end
#0
$dumpvars
b0 ^
0]
0\
0[
0Z
0Y
0W
0V
0U
0T
0S
0Q
0P
0O
0N
0M
0K
0J
0I
0H
0G
0E
0D
0C
0B
0A
0?
0>
0=
0<
0;
09
08
07
06
05
03
02
01
00
0/
b0 ,
b0 +
b0 *
b0 )
b0 (
bx '
0&
b0 %
b0 $
0"
b0 !
$end
#10000
18
1>
1D
1J
1P
1V
b11111110 !
b11111110 +
1\
17
1=
1C
1I
1O
1U
1[
1"
13
19
1?
1E
1K
1Q
1W
b111111110 ,
1]
10
16
1<
1B
1H
1N
1T
1Z
1/
15
1;
1A
1G
1M
1S
1Y
b11111111 %
b11111111 *
b11111111 $
b11111111 )
b0 '
#20000
08
0>
0D
0J
0P
0V
b0 !
b0 +
0\
06
0<
0B
0H
0N
0T
0Z
b1 %
b1 *
b111111110 '
#30000
0C
0U
0"
1>
0?
1P
0Q
1\
0]
07
0=
0I
0O
0[
12
03
08
09
0D
0E
0J
0K
b10100101 !
b10100101 +
0V
b0 ,
0W
1Z
0/
05
0A
0G
0S
0Y
b10000001 %
b10000001 *
b100100 $
b100100 )
b100000000 '
#40000
1J
1I
1E
1C
0>
1?
1=
19
17
0D
0\
13
08
b1110001 !
b1110001 +
1V
11
1<
1B
0Z
1/
15
0;
1S
b11111 ,
1&
b1101 %
b1101 *
b1100011 $
b1100011 )
b1 ^
b10100101 '
#50000
0\
0[
1V
0W
0U
1P
0Q
0I
0O
02
1D
0E
b1111000 !
b1111000 +
1J
b1111 ,
0K
00
16
0<
0B
1H
05
1;
b10010 %
b10010 *
b1100101 $
b1100101 )
b10 ^
b1110001 '
#60000
1\
1[
0V
1W
1U
0P
1Q
1O
0J
1K
1I
1>
b10000100 !
b10000100 +
0D
b11111111 ,
1E
1<
1N
1T
1A
0M
0S
b1110110 %
b1110110 *
b1101 $
b1101 )
b11 ^
b1111000 '
#70000
0\
0[
1V
0W
0U
0>
1P
0Q
0=
0O
1"
18
09
1D
b1111010 !
b1111010 +
1J
0K
b100011011 ,
1]
06
1B
0H
0N
0T
1Z
1M
1S
1Y
b10001100 %
b10001100 *
b11101101 $
b11101101 )
b100 ^
b10000100 '
#80000
0J
1\
0>
0I
1[
07
0=
0E
0V
1W
12
03
18
09
b10001011 !
b10001011 +
0P
01
10
0B
1T
0/
15
0A
0M
b110001000 ,
0&
b11000101 %
b11000101 *
b11000110 $
b11000110 )
b101 ^
b101111010 '
#90000
1>
1=
1V
08
19
1U
17
1J
1Q
0\
b1011100 !
b1011100 +
02
b111001110 ,
13
16
1H
1N
0Z
1/
05
1M
b1110111 %
b1110111 *
b11100101 $
b11100101 )
b110 ^
b110001011 '
#100000
1O
1[
0J
1K
1W
07
1I
1U
12
03
0>
1\
08
0D
1E
0P
b111111100 ,
1Q
b10000001 !
b10000001 +
0V
00
0<
1Z
15
1A
0M
0S
b11110010 %
b11110010 *
b10001111 $
b10001111 )
b111 ^
b101011100 '
#110000
0I
1D
0E
0U
0C
18
1P
0Q
1>
0?
17
0O
0=
13
0J
0K
02
09
b10101110 !
b10101110 +
0V
11
10
06
1<
0H
0N
0/
05
0;
1M
1S
b110000011 ,
1&
b11000101 %
b11000101 *
b11101000 $
b11101000 )
b1000 ^
b110000001 '
#120000
1O
0"
1K
1V
0]
1I
1U
1C
0[
1D
1E
1P
1Q
1\
0>
1?
b11101010 !
b11101010 +
0J
0W
01
1B
1N
0T
0Z
1/
1;
1G
0S
b1111010 ,
0&
b101101 %
b101101 *
b10111101 $
b10111101 )
b1001 ^
b110101110 '
#130000
0I
0U
08
1>
0E
0Q
07
1=
0C
0O
0[
12
03
1P
19
0?
1D
0J
0K
1V
b100 ,
0W
b1101101 !
b1101101 +
0\
00
16
0<
0N
15
0;
0A
0G
1S
0Y
b1010 %
b1010 *
b1100011 $
b1100011 )
b1010 ^
b11101010 '
#140000
0>
1U
0=
0P
1Q
1\
02
18
b1000000 ,
09
b11001010 !
b11001010 +
1V
1N
1Z
0/
05
0S
b10101010 %
b10101010 *
b100000 $
b100000 )
b1011 ^
b1101101 '
#150000
1C
1P
1?
0V
1O
1=
0U
12
1D
1K
08
19
b10101001 !
b10101001 +
0>
b101100 ,
0Q
10
0B
1H
0N
0Z
15
1;
1G
0M
1Y
b10011 %
b10011 *
b10010110 $
b10010110 )
b1100 ^
b11001010 '
#160000
0V
18
0I
0O
0U
1[
17
0C
1D
0E
1J
0K
1P
0Q
1W
02
13
1>
b10000110 ,
0?
b10111110 !
b10111110 +
1\
1B
0H
1N
1T
1/
0;
1S
0Y
b1101011 %
b1101011 *
b1010011 $
b1010011 )
b1101 ^
b10101001 '
#170000
1I
0D
1E
08
1C
0"
07
0[
0>
1?
1\
0]
12
03
b10110001 !
b10110001 +
1J
0W
11
00
1<
0T
1Z
0/
0G
0S
b11101 ,
1&
b10101110 %
b10101110 *
b10 $
b10 )
b1110 ^
b10111110 '
#180000
18
17
b11111 ,
13
b11110011 !
b11110011 +
1V
10
0<
0B
0Z
1/
1;
1A
1S
1Y
b100011 %
b100011 *
b11001111 $
b11001111 )
b1111 ^
b10110001 '
#190000
1"
0\
1]
0C
1[
1>
0?
0V
1W
0=
1U
09
0P
1Q
07
1O
03
18
0D
b111 !
b111 +
0J
b111110001 ,
1K
00
06
1<
1B
1H
0/
0;
b111100 %
b111100 *
b11001010 $
b11001010 )
b10000 ^
b11110011 '
#200000
0"
1\
0]
0[
1V
0W
0I
0O
0U
0>
1D
0E
0J
0K
b11001011 !
b11001011 +
0P
0Q
01
10
0<
0B
0H
0N
1T
0S
b0 ,
0&
b1000001 %
b1000001 *
b10001010 $
b10001010 )
b10001 ^
b100000111 '
#210000
1"
0\
1]
1[
0V
1W
1U
1Q
1O
1K
17
1I
02
13
0D
1E
18
0J
b10 !
b10 +
0P
11
1B
0T
1Z
05
1G
1M
1S
0Y
b111110011 ,
1&
b10001001 %
b10001001 *
b1111000 $
b1111000 )
b10010 ^
b11001011 '
#220000
0[
1V
0W
0U
1P
0Q
0O
08
1D
1>
1J
0K
07
1C
1=
0I
12
03
1?
19
b100001101 ,
0E
b1111101 !
b1111101 +
0\
00
16
1<
0B
1T
15
1;
0A
0S
1Y
b11000110 %
b11000110 *
b10110110 $
b10110110 )
b10011 ^
b100000010 '
#230000
0D
0C
1O
0?
0J
1K
1U
0"
0=
1I
02
1>
1P
1Q
1V
1\
0]
b11100110 !
b11100110 +
18
09
1E
01
0<
1B
1N
0T
0Z
05
1A
b1110000 ,
0&
b101010 %
b101010 *
b10111100 $
b10111100 )
b10100 ^
b101111101 '
#240000
0U
0Q
0O
0"
1J
0K
1\
0]
17
0I
0[
13
18
1P
12
0E
b11110111 !
b11110111 +
1V
0W
11
10
06
1<
0B
0N
1Z
1/
0;
0A
1S
0Y
b11 ,
1&
b10000101 %
b10000101 *
b1110001 $
b1110001 )
b10101 ^
b11100110 '
#250000
08
07
1I
1O
1U
1=
03
1>
1E
1J
1K
1P
1Q
0\
19
b1110101 !
b1110101 +
1V
01
00
16
0<
1B
1H
1N
0Z
15
1A
0S
b1110100 ,
0&
b111010 %
b111010 *
b111011 $
b111011 )
b10110 ^
b11110111 '
#260000
1"
18
1]
0D
0J
17
1[
0=
0C
0I
13
0V
1W
0\
09
1>
0?
0E
b111 !
b111 +
0P
11
10
06
0B
1T
1Z
05
1;
0A
0M
b111100011 ,
1&
b11110001 %
b11110001 *
b10101 $
b10101 )
b10111 ^
b1110101 '
#270000
0J
0I
0E
0C
0U
1>
0?
1P
0Q
07
0"
0=
0O
03
1D
1\
0]
18
09
b10000001 ,
0K
b10101111 !
b10101111 +
0V
00
1<
1B
0H
0N
0Z
0/
15
0;
0G
1M
1S
b1001100 %
b1001100 *
b1100010 $
b1100010 )
b11000 ^
b100000111 '
#280000
1U
0P
1Q
1O
1K
1\
1I
1[
1"
0J
0D
1E
b10000111 !
b10000111 +
0V
1W
1]
01
0<
1H
1N
1Z
1/
1;
1A
0M
0S
1Y
b111110000 ,
0&
b11111000 %
b11111000 *
b10001111 $
b10001111 )
b11001 ^
b10101111 '
#290000
0"
0]
0[
1D
1V
0W
1C
0U
0>
1?
1P
b111000 ,
0Q
1\
b11111011 !
b11111011 +
1J
1<
0N
0Z
1G
b1011100 %
b1011100 *
b10011111 $
b10011111 )
b11010 ^
b110000111 '
#300000
0P
0D
17
0O
0C
02
13
0K
b11010010 !
b11010010 +
18
b10010 ,
0?
10
0<
0H
05
0;
0G
b1001001 %
b1001001 *
b10001001 $
b10001001 )
b11011 ^
b11111011 '
#310000
1D
1C
1"
1?
0J
1P
0\
1]
1=
0I
1O
1[
12
08
19
0>
0E
1K
b101001 !
b101001 +
0V
1W
11
0B
1H
15
1;
0A
1G
1S
b110101111 ,
1&
b1010001 %
b1010001 *
b11010111 $
b11010111 )
b11100 ^
b11010010 '
#320000
0C
1>
0?
0=
0"
18
09
0J
0P
1\
0]
07
0I
0O
0[
03
1D
0E
0K
b11001111 !
b11001111 +
1V
b1 ,
0W
00
16
0H
1Z
0/
05
1A
0G
0S
0Y
b11000010 %
b11000010 *
b1100 $
b1100 )
b11101 ^
b100101001 '
#330000
1J
1I
1[
1=
0D
1E
1P
0V
1W
08
19
1C
1O
1U
17
1>
1?
1K
1Q
b10110101 !
b10110101 +
1\
b11111111 ,
13
10
06
1<
1B
1H
1N
0T
0Z
1/
15
0A
1G
1M
1S
b111101 %
b111101 *
b1110111 $
b1110111 )
b11110 ^
b11001111 '
#340000
0J
1V
02
b11101100 !
b11101100 +
1D
0H
1T
0/
1A
b1101101 %
b1101101 *
b1111110 $
b1111110 )
b11111 ^
b10110101 '
#350000
0[
0W
0U
0"
18
0>
0D
1J
0Q
1\
b111111 ,
0]
12
b11110011 !
b11110011 +
1V
16
0<
0B
1H
0N
1Z
1/
0M
0S
b11010011 %
b11010011 *
b11111 $
b11111 )
b100000 ^
b11101100 '
#360000
0C
1U
1[
0D
1\
02
08
1>
0?
0P
1Q
b11010100 !
b11010100 +
1V
b11110111 ,
1W
1B
0Z
0/
05
0;
1M
1S
b1011011 %
b1011011 *
b1111000 $
b1111000 )
b100001 ^
b11110011 '
#370000
0\
1D
0[
1C
0J
1P
0W
18
b1101010 !
b1101010 +
0>
b1111111 ,
1?
00
0H
1N
0T
1/
15
1;
0S
b101010 %
b101010 *
b111111 $
b111111 )
b100010 ^
b11010100 '
#380000
0V
08
0P
0U
1"
07
0O
1>
0Q
1]
03
0D
b10100 !
b10100 +
1J
0K
01
1<
0N
1Z
0/
0A
0G
0M
1Y
b100011100 ,
0&
b10001110 %
b10001110 *
b10000110 $
b10000110 )
b100011 ^
b1101010 '
#390000
1[
1W
1P
1U
1"
1O
12
1Q
0\
1]
0>
0J
1K
b100001 !
b100001 +
0V
11
0B
1N
0Z
0;
1A
1G
1M
1S
b111111101 ,
1&
b100110 %
b100110 *
b11111010 $
b11111010 )
b100100 ^
b100010100 '
#400000
0"
18
0P
1\
0]
17
0O
0[
02
13
1J
0K
b11010010 !
b11010010 +
1V
0W
01
10
1B
1/
0A
0G
0S
b1011110 ,
0&
b101111 %
b101111 *
b10100011 $
b10100011 )
b100101 ^
b100100001 '
#410000
1P
0V
1O
0U
1[
08
1>
0J
1K
0Q
1W
b10100100 !
b10100100 +
1\
11
00
06
0B
0N
1T
1;
1A
1G
0M
1S
0Y
b10111111 ,
1&
b1000100 %
b1000100 *
b1011111 $
b1011111 )
b100110 ^
b11010010 '
#420000
0V
0U
0O
1"
18
1P
0Q
0>
b10110010 !
b10110010 +
1J
0K
b110011111 ,
1]
16
1N
1Z
0;
0G
1Y
b11100110 %
b11100110 *
b11001011 $
b11001011 )
b100111 ^
b10100100 '
#430000
0C
1"
1>
0?
1]
0=
1U
1[
09
0D
0P
1Q
0V
1W
b10110 !
b10110 +
0\
01
10
06
1B
05
1M
0S
0Y
b111010010 ,
0&
b11101101 %
b11101101 *
b101001 $
b101001 )
b101000 ^
b110110010 '
#440000
0P
1D
0O
1C
0I
1J
0K
b11010 !
b11010 +
0>
1?
b111001010 ,
0E
0B
1H
0T
1;
0A
1S
b10110101 %
b10110101 *
b1100101 $
b1100101 )
b101001 ^
b100010110 '
#450000
0O
08
1J
0K
07
0U
0"
0C
0I
12
03
1P
0Q
0V
1\
0]
1>
0?
b10111101 !
b10111101 +
1D
b10000000 ,
0E
00
0H
0N
1T
0Z
0;
1A
1G
b1000100 %
b1000100 *
b1111001 $
b1111001 )
b101010 ^
b100011010 '
#460000
18
1V
17
1=
1I
1U
0"
0[
13
19
1>
0D
1E
0P
1Q
1\
0]
02
b11010110 !
b11010110 +
1J
0W
11
10
16
0<
1B
1N
0T
1Z
0/
15
0G
0S
b1010111 ,
1&
b10101011 %
b10101011 *
b101010 $
b101010 )
b101011 ^
b10111101 '
#470000
0=
09
0D
1P
07
0C
1O
0U
0[
1"
03
18
1>
0?
1K
0Q
1V
0W
b1110110 !
b1110110 +
0\
1]
01
00
1H
0N
05
1;
1G
0M
1S
1Y
b100110000 ,
0&
b10011010 %
b10011010 *
b11011100 $
b11011100 )
b101100 ^
b11010110 '
#480000
1D
0P
1C
0O
0>
1?
0K
17
1[
1"
1=
0I
13
0V
1W
0\
1]
18
19
0E
b11010 !
b11010 +
1J
11
1<
0B
1T
0Z
1/
15
0;
0A
0G
b110001111 ,
1&
b1010110 %
b1010110 *
b11000011 $
b11000011 )
b101101 ^
b101110110 '
#490000
1I
0[
0"
0D
1E
1J
1V
0W
1P
b1110010 !
b1110010 +
0\
b11111 ,
0]
0<
1B
0H
0T
1;
1M
0Y
b1010 %
b1010 *
b1100111 $
b1100111 )
b101110 ^
b100011010 '
#500000
1\
1[
0V
1W
08
0=
1U
07
0C
1O
09
1P
1Q
12
03
0>
0?
b10110001 !
b10110001 +
0D
1K
01
10
06
1H
1N
1T
0/
05
0;
1A
1G
0S
b11110000 ,
0&
b1111001 %
b1111001 *
b111000 $
b111000 )
b101111 ^
b1110010 '
#510000
0\
0J
0U
0[
0I
1"
18
0Q
0V
0W
b100111 !
b100111 +
1>
0E
b100100000 ,
1]
16
0B
0N
0T
1Z
1;
0A
0M
1Y
b10010011 %
b10010011 *
b10010100 $
b10010100 )
b110000 ^
b10110001 '
#520000
1=
1J
08
19
1I
1[
17
1"
1E
1W
02
13
1>
b110100 !
b110100 +
0\
b110110110 ,
1]
1B
1T
1/
0;
1A
1S
0Y
b11011011 %
b11011011 *
b1011001 $
b1011001 )
b110001 ^
b100100111 '
#530000
0D
1V
0=
0C
1U
18
09
1>
0?
0J
b1000110 !
b1000110 +
0P
b111110010 ,
1Q
06
1<
0H
1N
0Z
1Y
b1101101 %
b1101101 *
b11011001 $
b11011001 )
b110010 ^
b100110100 '
#540000
1[
1W
1U
0P
1Q
1O
1C
0J
1K
08
0>
1?
1I
07
1=
0D
1E
0V
1\
b10000001 !
b10000001 +
12
03
19
11
00
16
0B
1H
0T
1Z
0/
15
0G
b111111101 ,
1&
b10110110 %
b10110110 *
b11001010 $
b11001010 )
b110011 ^
b101000110 '
#550000
0\
0[
1V
0W
0=
0O
0U
0"
0I
18
09
0J
0K
0P
0Q
0]
0>
b1001011 !
b1001011 +
1D
b1001 ,
0E
06
0H
0N
0Z
1;
0A
0Y
b100 %
b100 *
b1000110 $
b1000110 )
b110100 ^
b110000001 '
#560000
1"
1]
0P
1[
0O
0V
1W
0K
1U
17
0C
0I
1J
1Q
0\
02
13
18
1>
0?
b11110 !
b11110 +
1D
b111000011 ,
0E
1H
1N
1Z
1/
05
0;
1A
1M
b10110100 %
b10110100 *
b1101001 $
b1101001 )
b110101 ^
b1001011 '
#570000
08
1I
0"
07
0[
0D
1E
1J
0\
0]
12
03
b1010101 !
b1010101 +
1V
0W
01
10
1B
0H
0Z
0/
0S
b1010000 ,
0&
b101101 %
b101101 *
b101000 $
b101000 )
b110110 ^
b100011110 '
#580000
0V
0U
1P
0Q
b110111 !
b110111 +
18
11
00
0<
0N
15
1;
b10001 ,
1&
b1000 %
b1000 *
b101110 $
b101110 )
b110111 ^
b1010101 '
#590000
1"
1]
1[
1W
1U
17
1O
1P
1Q
02
13
18
0J
1K
0V
b100110 !
b100110 +
0\
01
10
1N
1/
05
1G
1S
1Y
b111110010 ,
0&
b101001 %
b101001 *
b11111101 $
b11111101 )
b111000 ^
b110111 '
#600000
1P
0[
1C
1O
1V
0W
08
0>
1?
0J
1K
0U
07
1=
1I
0Q
0\
03
19
b1100000 !
b1100000 +
0D
b100111100 ,
1E
00
16
1H
0N
1T
1Z
0/
15
0A
0G
0M
0S
b11011010 %
b11011010 *
b10000110 $
b10000110 )
b111001 ^
b100100110 '
#610000
0P
0C
0O
1>
0?
1J
0K
1\
0=
0I
1U
1[
0"
18
09
0D
0E
1Q
b11010110 !
b11010110 +
1V
1W
b11000000 ,
0]
06
0B
1N
0Z
1M
1S
0Y
b1110000 %
b1110000 *
b1100110 $
b1100110 )
b111010 ^
b101100000 '
#620000
1D
1C
1[
0>
1?
1W
1=
1I
1U
1O
1"
12
08
19
1E
0P
1Q
1J
1K
0V
b11001 !
b11001 +
0\
1]
11
16
1<
1B
0N
0;
1A
1G
0S
1Y
b111111101 ,
1&
b1011110 %
b1011110 *
b10111010 $
b10111010 )
b111011 ^
b11010110 '
#630000
0J
0I
0"
0E
1\
0]
0C
0[
1>
0?
1V
0W
0=
0U
18
09
1D
b11101111 !
b11101111 +
1P
0Q
01
0<
0T
1/
05
1;
0A
0M
1S
b100000 ,
0&
b11010 %
b11010 *
b11010101 $
b11010101 )
b111100 ^
b100011001 '
#640000
17
1C
1=
1U
02
13
1>
1?
1D
18
19
0P
1Q
b11001110 !
b11001110 +
1V
11
1<
0B
1Z
15
1M
0S
0Y
b1101111 ,
1&
b10010110 %
b10010110 *
b110111 $
b110111 )
b111101 ^
b11101111 '
#650000
08
07
0O
0P
12
03
b11011101 !
b11011101 +
1J
b1001101 ,
0K
1N
0/
0G
b10110110 %
b10110110 *
b100110 $
b100110 )
b111110 ^
b11001110 '
#660000
1P
1O
0>
0J
1K
0=
1I
0U
0[
1"
18
09
0D
1E
0Q
1V
0W
b1100011 !
b1100011 +
0\
b100111001 ,
1]
0H
0N
05
1A
1G
0M
1S
1Y
b10000110 %
b10000110 *
b11011100 $
b11011100 )
b111111 ^
b11011101 '
#670000
1C
1[
1=
1U
1"
0>
1?
1D
1J
1V
1W
08
19
0P
1Q
b1011001 !
b1011001 +
0\
1]
01
10
0<
1B
1H
1T
15
1M
0Y
b111111100 ,
0&
b11011011 %
b11011011 *
b1111110 $
b1111110 )
b1000000 ^
b101100011 '
#680000
0D
0=
0C
1P
18
09
b1110011 !
b1110011 +
0>
b111110000 ,
0?
00
1N
1/
05
0;
b11111010 %
b11111010 *
b1111001 $
b1111001 )
b1000001 ^
b101011001 '
#690000
1D
0V
1C
0U
1?
0Q
1=
0"
0O
08
19
1\
0]
0K
17
0[
0I
13
1J
0W
0>
0E
b10111001 !
b10111001 +
1P
11
10
06
0B
0H
0T
15
1;
0A
0M
0S
b1111 ,
1&
b10100001 %
b10100001 *
b10111 $
b10111 )
b1000010 ^
b101110011 '
#700000
1V
0D
1U
1"
0C
0P
1Q
0\
1]
1>
0?
07
1O
1[
0=
03
0J
1K
1W
b1000101 !
b1000101 +
08
09
01
1<
1H
1T
0/
05
0;
1S
b111100000 ,
0&
b11110101 %
b11110101 *
b1010000 $
b1010000 )
b1000011 ^
b10111001 '
#710000
0"
1\
0]
0[
0W
0U
18
1P
0Q
17
0O
0>
02
13
1D
b10 ,
0K
b11101010 !
b11101010 +
1V
0<
0H
0N
1/
1A
0G
1M
0S
b11000001 %
b11000001 *
b101001 $
b101001 )
b1000100 ^
b101000101 '
#720000
1O
0>
1K
0=
1I
07
18
09
0D
1E
12
b110000 ,
03
0J
b11100011 !
b11100011 +
1P
16
1B
0Z
0/
1G
0M
1Y
b1001011 %
b1001011 *
b10011000 $
b10011000 )
b1000101 ^
b11101010 '
#730000
0[
1V
0W
1"
0O
0U
0\
1]
1>
1J
0K
b1110111 !
b1110111 +
1P
0Q
11
00
0T
1Z
1;
0G
1M
1S
b100010001 ,
1&
b10001010 %
b10001010 *
b11101100 $
b11101100 )
b1000110 ^
b11100011 '
#740000
1U
08
0P
1Q
0>
b1010001 !
b1010001 +
1V
01
10
06
1N
0;
0S
b101010000 ,
0&
b10101001 %
b10101001 *
b10101000 $
b10101000 )
b1000111 ^
b101110111 '
#750000
1>
1J
1=
1C
1I
0[
0U
0"
02
19
1?
0D
1E
1V
0W
1P
0Q
b11110100 !
b11110100 +
1\
b11100 ,
0]
00
16
1<
0B
1T
15
1;
0M
0Y
b11100110 %
b11100110 *
b1110 $
b1110 )
b1001000 ^
b101010001 '
#760000
0C
1U
0?
0D
1V
0\
b1010100 !
b1010100 +
0P
b1010100 ,
1Q
0<
1B
0T
0Z
0;
1M
b101010 %
b101010 *
b101010 $
b101010 )
b1001001 ^
b11110100 '
#770000
0D
1V
0=
0C
1O
1U
18
09
1>
0?
1K
0P
b1110000 ,
1Q
b11010110 !
b11010110 +
1\
06
1H
1;
1G
0M
1Y
b111000 %
b111000 *
b10011110 $
b10011110 )
b1001010 ^
b1010100 '
#780000
0V
0O
0U
1"
1[
12
0K
0P
0Q
1\
1]
b10010011 !
b10010011 +
0>
1W
11
16
0H
0N
1T
1Z
05
0;
0G
1S
b110010001 ,
1&
b11001010 %
b11001010 *
b11001000 $
b11001000 )
b1001011 ^
b11010110 '
#790000
1C
1J
1?
1I
17
1=
0>
0D
1E
13
18
b110011111 ,
19
1P
b110011 !
b110011 +
0\
10
1<
0B
1/
15
1M
0Y
b11000111 %
b11000111 *
b1101011 $
b1101011 )
b1001100 ^
b110010011 '
#800000
0I
1D
0E
0C
1>
0?
0=
0U
09
1P
0Q
07
0O
0[
03
18
1J
0K
1V
b100000001 ,
0W
b1111111 !
b1111111 +
0\
00
06
0/
1G
0S
1Y
b11000100 %
b11000100 *
b10111010 $
b10111010 )
b1001101 ^
b100110011 '
#810000
1U
0P
1Q
1O
0J
b101100001 ,
1K
1V
b1000111 !
b1000111 +
0D
1H
1N
0T
0A
0M
b10110100 %
b10110100 *
b10010010 $
b10010010 )
b1001110 ^
b101111111 '
#820000
1I
1E
1C
1U
0>
1?
1\
0P
1Q
1=
1[
1O
02
08
19
0D
0V
1W
b10000000 !
b10000000 +
0J
1K
01
16
0<
1B
1T
1;
0G
b111111100 ,
0&
b11111010 %
b11111010 *
b10000110 $
b10000110 )
b1001111 ^
b101000111 '
#830000
1I
0D
1E
1C
0"
0>
1?
0]
17
1=
0[
13
08
19
1V
0W
1J
1P
b11110000 !
b11110000 +
1\
11
10
06
1<
0T
0;
1G
1M
0Y
b1111111 ,
1&
b10111101 %
b10111101 *
b110010 $
b110010 )
b1010000 ^
b110000000 '
#840000
0J
0I
1D
0E
0C
1>
0?
0V
0=
0U
18
09
0Q
07
0O
1[
1"
12
03
0K
1P
1W
b10101111 !
b10101111 +
1\
b110000001 ,
1]
00
16
0<
0H
0N
1T
05
1;
0G
1S
1Y
b11001010 %
b11001010 *
b11100100 $
b11100100 )
b1010001 ^
b11110000 '
#850000
b101111 !
b101111 +
0\
0[
0W
01
1<
0T
1/
0;
0S
b100000000 ,
0&
b10001110 %
b10001110 *
b10100001 $
b10100001 )
b1010010 ^
b110101111 '
#860000
1C
0>
1?
1J
17
1=
1I
0"
13
1V
18
19
1D
1E
b11111011 !
b11111011 +
1\
0]
11
10
1N
1T
15
1A
0M
0Y
b11111 ,
1&
b11101111 %
b11101111 *
b1011 $
b1011 )
b1010011 ^
b100101111 '
#870000
0=
1[
09
0J
0V
1W
07
0I
1O
1U
03
18
0E
1\
0>
1K
b10101011 !
b10101011 +
1P
1Q
01
06
0B
1H
0Z
0/
1;
0A
1G
1M
b11101000 ,
0&
b1110101 %
b1110101 *
b110110 $
b110110 )
b1010100 ^
b11111011 '
#880000
0[
1V
0W
0U
0D
1J
0Q
0"
0C
1I
0O
1P
b11110011 !
b11110011 +
1\
0]
0?
1E
b10000 ,
0K
00
0<
1B
0H
0N
0T
1Z
1/
0;
1A
0G
1S
b10001000 %
b10001000 *
b1101011 $
b1101011 )
b1010101 ^
b10101011 '
#890000
1>
0J
17
1=
0I
1O
1"
02
13
18
19
1D
0E
1K
1P
0V
b101110 !
b101110 +
0\
1]
11
16
0B
1H
1G
0M
0S
1Y
b100100111 ,
1&
b10010010 %
b10010010 *
b10011011 $
b10011011 )
b1010110 ^
b11110011 '
