Módulo 4 - Ejercicios/ejercicio_3/rca4.sv
`timescale 1ns/1ps

module rca4 #(
    parameter N = 4
) (
    input  logic [N-1:0] a,
    input  logic [N-1:0] b,
    input  logic         cin,
    output logic [N-1:0] s,
    output logic         cout
);
    logic [N:0] c;
    assign c[0] = cin;

    genvar i;
    generate 
        for (i = 0; i < N; i = i + 1) begin : fa_chain
            assign {c[i+1], s[i]} = a[i] + b[i] + c[i];
        end
    endgenerate

    assign cout = c[N];
endmodule

Módulo 4 - Ejercicios/ejercicio_3/csla16.sv
`timescale 1ns/1ps

module csla16 #(
    parameter N = 16
) (
    input  logic [N-1:0] a,
    input  logic [N-1:0] b,
    input  logic         cin,
    output logic [N-1:0] s,
    output logic         cout
);
    // Cables intermedios para los acarreos entre etapas
    logic c4, c8, c12;

    // --- Bloque 0 (Bits 3:0) ---
    // El primer bloque es un RCA normal porque ya conocemos el carry in real
    rca4 b0 (
        .a(a[3:0]), .b(b[3:0]), .cin(cin), 
        .s(s[3:0]), .cout(c4)
    );

    // --- Bloque 1 (Bits 7:4) ---
    logic [3:0] s1_0, s1_1;
    logic       c8_0, c8_1;
    
    rca4 b1_0 (.a(a[7:4]), .b(b[7:4]), .cin(1'b0), .s(s1_0), .cout(c8_0));
    rca4 b1_1 (.a(a[7:4]), .b(b[7:4]), .cin(1'b1), .s(s1_1), .cout(c8_1));
    
    assign s[7:4] = (c4) ? s1_1 : s1_0;
    assign c8     = (c4) ? c8_1 : c8_0;

    // --- Bloque 2 (Bits 11:8) ---
    logic [3:0] s2_0, s2_1;
    logic       c12_0, c12_1;
    
    rca4 b2_0 (.a(a[11:8]), .b(b[11:8]), .cin(1'b0), .s(s2_0), .cout(c12_0));
    rca4 b2_1 (.a(a[11:8]), .b(b[11:8]), .cin(1'b1), .s(s2_1), .cout(c12_1));
    
    assign s[11:8] = (c8) ? s2_1 : s2_0;
    assign c12     = (c8) ? c12_1 : c12_0;

    // --- Bloque 3 (Bits 15:12) ---
    logic [3:0] s3_0, s3_1;
    logic       cout_0, cout_1;
    
    rca4 b3_0 (.a(a[15:12]), .b(b[15:12]), .cin(1'b0), .s(s3_0), .cout(cout_0));
    rca4 b3_1 (.a(a[15:12]), .b(b[15:12]), .cin(1'b1), .s(s3_1), .cout(cout_1));
    
    assign s[15:12] = (c12) ? s3_1 : s3_0;
    assign cout     = (c12) ? cout_1 : cout_0;
endmodule

Módulo 4 - Ejercicios/ejercicio_3/tb_csla.sv
`timescale 1ns/1ps

module tb_csla;
    logic [15:0] a, b, s;
    logic        cin, cout;
    logic [16:0] expected;
    int          errors = 0;

    csla16 dut (
        .a   (a),
        .b   (b),
        .cin (cin),
        .s   (s),
        .cout(cout)
    );

    task check_result(input string name);
        expected = a + b + cin;
        if ({cout, s} !== expected) begin
            $display("[FAIL] %s: a=%h, b=%h, cin=%b | Obtenido: {cout=%b, s=%h}, Esperado: %h", 
                     name, a, b, cin, cout, s, expected);
            errors++;
        end
    endtask

    initial begin
        $dumpfile("csla.vcd");
        $dumpvars(0, tb_csla);

        // 1. Borde inferior: 0 + 0
        a = 0; b = 0; cin = 0; #10;
        check_result("Borde Inferior");

        // 2. Borde superior: max + max
        a = '1; b = '1; cin = 0; #10;
        check_result("Borde Superior");

        // 3. Caso con Carry-out = 1
        a = 16'hFFFF; b = 16'h0001; cin = 0; #10;
        check_result("Carry-out en 1");

        // 4. 1000 casos aleatorios (segun consigna ej 2/3)
        for (int i = 0; i < 1000; i++) begin
            a   = $urandom;
            b   = $urandom;
            cin = $urandom_range(0, 1);
            #10;
            check_result("Random");
        end

        if (errors == 0) begin
            $display("=========================================");
            $display("PASS: Todos los casos evaluados con exito.");
            $display("=========================================");
        end else begin
            $display("=========================================");
            $display("FAIL: Se encontraron %0d errores.", errors);
            $display("=========================================");
        end

        $finish;
    end
endmodule

Módulo 4 - Ejercicios/ejercicio_3/csla.vcd
$date
	Wed Aug 26 15:05:23 2026
$end
$version
	Icarus Verilog
$end
$timescale
	1ps
$end
$scope module tb_csla $end
$var wire 16 ! s [15:0] $end
$var wire 1 " cout $end
$var reg 16 # a [15:0] $end
$var reg 16 $ b [15:0] $end
$var reg 1 % cin $end
$var reg 17 & expected [16:0] $end
$var integer 32 ' errors [31:0] $end
$scope module dut $end
$var wire 16 ( a [15:0] $end
$var wire 16 ) b [15:0] $end
$var wire 1 % cin $end
$var wire 4 * s3_1 [3:0] $end
$var wire 4 + s3_0 [3:0] $end
$var wire 4 , s2_1 [3:0] $end
$var wire 4 - s2_0 [3:0] $end
$var wire 4 . s1_1 [3:0] $end
$var wire 4 / s1_0 [3:0] $end
$var wire 16 0 s [15:0] $end
$var wire 1 1 cout_1 $end
$var wire 1 2 cout_0 $end
$var wire 1 " cout $end
$var wire 1 3 c8_1 $end
$var wire 1 4 c8_0 $end
$var wire 1 5 c8 $end
$var wire 1 6 c4 $end
$var wire 1 7 c12_1 $end
$var wire 1 8 c12_0 $end
$var wire 1 9 c12 $end
$var parameter 32 : N $end
$scope module b0 $end
$var wire 4 ; a [3:0] $end
$var wire 4 < b [3:0] $end
$var wire 1 % cin $end
$var wire 4 = s [3:0] $end
$var wire 1 6 cout $end
$var wire 5 > c [4:0] $end
$var parameter 32 ? N $end
$scope begin fa_chain[0] $end
$var parameter 2 @ i $end
$upscope $end
$scope begin fa_chain[1] $end
$var parameter 2 A i $end
$upscope $end
$scope begin fa_chain[2] $end
$var parameter 3 B i $end
$upscope $end
$scope begin fa_chain[3] $end
$var parameter 3 C i $end
$upscope $end
$upscope $end
$scope module b1_0 $end
$var wire 4 D a [3:0] $end
$var wire 4 E b [3:0] $end
$var wire 1 F cin $end
$var wire 4 G s [3:0] $end
$var wire 1 4 cout $end
$var wire 5 H c [4:0] $end
$var parameter 32 I N $end
$scope begin fa_chain[0] $end
$var parameter 2 J i $end
$upscope $end
$scope begin fa_chain[1] $end
$var parameter 2 K i $end
$upscope $end
$scope begin fa_chain[2] $end
$var parameter 3 L i $end
$upscope $end
$scope begin fa_chain[3] $end
$var parameter 3 M i $end
$upscope $end
$upscope $end
$scope module b1_1 $end
$var wire 4 N a [3:0] $end
$var wire 4 O b [3:0] $end
$var wire 1 P cin $end
$var wire 4 Q s [3:0] $end
$var wire 1 3 cout $end
$var wire 5 R c [4:0] $end
$var parameter 32 S N $end
$scope begin fa_chain[0] $end
$var parameter 2 T i $end
$upscope $end
$scope begin fa_chain[1] $end
$var parameter 2 U i $end
$upscope $end
$scope begin fa_chain[2] $end
$var parameter 3 V i $end
$upscope $end
$scope begin fa_chain[3] $end
$var parameter 3 W i $end
$upscope $end
$upscope $end
$scope module b2_0 $end
$var wire 4 X a [3:0] $end
$var wire 4 Y b [3:0] $end
$var wire 1 Z cin $end
$var wire 4 [ s [3:0] $end
$var wire 1 8 cout $end
$var wire 5 \ c [4:0] $end
$var parameter 32 ] N $end
$scope begin fa_chain[0] $end
$var parameter 2 ^ i $end
$upscope $end
$scope begin fa_chain[1] $end
$var parameter 2 _ i $end
$upscope $end
$scope begin fa_chain[2] $end
$var parameter 3 ` i $end
$upscope $end
$scope begin fa_chain[3] $end
$var parameter 3 a i $end
$upscope $end
$upscope $end
$scope module b2_1 $end
$var wire 4 b a [3:0] $end
$var wire 4 c b [3:0] $end
$var wire 1 d cin $end
$var wire 4 e s [3:0] $end
$var wire 1 7 cout $end
$var wire 5 f c [4:0] $end
$var parameter 32 g N $end
$scope begin fa_chain[0] $end
$var parameter 2 h i $end
$upscope $end
$scope begin fa_chain[1] $end
$var parameter 2 i i $end
$upscope $end
$scope begin fa_chain[2] $end
$var parameter 3 j i $end
$upscope $end
$scope begin fa_chain[3] $end
$var parameter 3 k i $end
$upscope $end
$upscope $end
$scope module b3_0 $end
$var wire 4 l a [3:0] $end
$var wire 4 m b [3:0] $end
$var wire 1 n cin $end
$var wire 4 o s [3:0] $end
$var wire 1 2 cout $end
$var wire 5 p c [4:0] $end
$var parameter 32 q N $end
$scope begin fa_chain[0] $end
$var parameter 2 r i $end
$upscope $end
$scope begin fa_chain[1] $end
$var parameter 2 s i $end
$upscope $end
$scope begin fa_chain[2] $end
$var parameter 3 t i $end
$upscope $end
$scope begin fa_chain[3] $end
$var parameter 3 u i $end
$upscope $end
$upscope $end
$scope module b3_1 $end
$var wire 4 v a [3:0] $end
$var wire 4 w b [3:0] $end
$var wire 1 x cin $end
$var wire 4 y s [3:0] $end
$var wire 1 1 cout $end
$var wire 5 z c [4:0] $end
$var parameter 32 { N $end
$scope begin fa_chain[0] $end
$var parameter 2 | i $end
$upscope $end
$scope begin fa_chain[1] $end
$var parameter 2 } i $end
$upscope $end
$scope begin fa_chain[2] $end
$var parameter 3 ~ i $end
$upscope $end
$scope begin fa_chain[3] $end
$var parameter 3 !" i $end
$upscope $end
$upscope $end
$upscope $end
$scope begin $ivl_for_loop0 $end
$var integer 32 "" i [31:0] $end
$upscope $end
$scope task check_result $end
$upscope $end
$upscope $end
$enddefinitions $end
$comment Show the parameter values. $end
$dumpall
b11 !"
b10 ~
b1 }
b0 |
b100 {
b11 u
b10 t
b1 s
b0 r
b100 q
b11 k
b10 j
b1 i
b0 h
b100 g
b11 a
b10 `
b1 _
b0 ^
b100 ]
b11 W
b10 V
b1 U
b0 T
b100 S
b11 M
b10 L
b1 K
b0 J
b100 I
b11 C
b10 B
b1 A
b0 @
b100 ?
b10000 :
$end
#0
$dumpvars
b0 ""
b1 z
b1 y
1x
b0 w
b0 v
b0 p
b0 o
0n
b0 m
b0 l
b1 f
b1 e
1d
b0 c
b0 b
b0 \
b0 [
0Z
b0 Y
b0 X
b1 R
b1 Q
1P
b0 O
b0 N
b0 H
b0 G
0F
b0 E
b0 D
b0 >
b0 =
b0 <
b0 ;
09
08
07
06
05
04
03
02
01
b0 0
b0 /
b1 .
b0 -
b1 ,
b0 +
b1 *
b0 )
b0 (
b0 '
bx &
0%
b0 $
b0 #
0"
b0 !
$end
#10000
b1110 =
b1111111111111110 !
b1111111111111110 0
b1110 /
b1110 G
15
b1110 -
b1110 [
19
b1110 +
b1110 o
1"
b1111 .
b1111 Q
b1111 ,
b1111 e
b1111 *
b1111 y
16
14
13
18
17
12
11
b11110 >
b11110 H
b11110 \
b11110 p
b11111 R
b11111 f
b11111 z
b1111 <
b1111 E
b1111 O
b1111 Y
b1111 c
b1111 m
b1111 w
b1111 ;
b1111 D
b1111 N
b1111 X
b1111 b
b1111 l
b1111 v
b1111111111111111 $
b1111111111111111 )
b1111111111111111 #
b1111111111111111 (
b0 &
#20000
04
08
02
b0 !
b0 0
b0 =
b0 H
b1111 /
b1111 G
b0 .
b0 Q
b0 \
b1111 -
b1111 [
b0 ,
b0 e
b0 p
b1111 +
b1111 o
b0 *
b0 y
b1 <
b0 E
b0 O
b0 Y
b0 c
b0 m
b0 w
b1 $
b1 )
b11111111111111110 &
#30000
18
19
03
05
0"
06
01
b11 -
b11 [
b11000 \
b100 ,
b100 e
b1110 p
b1001001110100101 !
b1001001110100101 0
b101 =
b0 >
b1010 /
b1010 G
b1011 .
b1011 Q
b1 R
b1000 +
b1000 o
b1001 *
b1001 y
b1111 z
b1000 E
b1000 O
b1110 Y
b1110 c
b101 m
b101 w
b100 ;
b10 D
b10 N
b101 X
b101 b
b11 l
b11 v
b101111010000001 $
b101111010000001 )
b11010100100100 #
b11010100100100 (
b10000000000000000 &
#40000
16
19
18
b1101000101110001 !
b1101000101110001 0
b1 =
b110 /
b110 G
b111 .
b111 Q
b1 -
b1 [
b11100 \
b10 ,
b10 e
b1100 +
b1100 o
b1101 *
b1101 y
b1101 <
b0 E
b0 O
b1011 Y
b1011 c
b111 m
b111 w
b11 ;
b110 D
b110 N
b110 X
b110 b
b101 l
b101 v
b11111 >
1%
b111101100001101 $
b111101100001101 )
b101011001100011 #
b101011001100011 (
b1 ""
b1001001110100101 &
#50000
09
0"
06
08
07
02
01
b1101011001111000 !
b1101011001111000 0
b1000 =
b1111 >
b111 /
b111 G
b1000 .
b1000 Q
b1111 R
b1 f
b110 -
b110 [
b0 \
b111 ,
b111 e
b1101 +
b1101 o
b0 p
b1110 *
b1110 y
b11 z
b10 <
b1 E
b1 O
b10 Y
b10 c
b101 m
b101 w
b101 ;
b100 X
b100 b
b1000 l
b1000 v
b101001000010010 $
b101001000010010 )
b1000010001100101 #
b1000010001100101 (
b10 ""
b1101000101110001 &
#60000
1"
12
11
16
b10 \
b1011111010000100 !
b1011111010000100 0
b100 =
b11111 >
b1110 -
b1110 [
b11 f
b1111 ,
b1111 e
b1011 +
b1011 o
b11000 p
b1100 *
b1100 y
b11111 z
b110 <
b111 E
b111 O
b1 Y
b1 c
b1111 m
b1111 w
b1101 ;
b0 D
b0 N
b1101 X
b1101 b
b1100 l
b1100 v
b1111000101110110 $
b1111000101110110 )
b1100110100001101 #
b1100110100001101 (
b11 ""
b1101011001111000 &
#70000
15
14
13
b11011 >
b100111101111010 !
b100111101111010 0
b1010 =
b110 /
b110 G
b10000 H
b111 .
b111 Q
b10001 R
b1110 \
b1110 -
b1110 [
b1111 f
b1111 ,
b1111 e
b11110 p
b100 +
b100 o
b101 *
b101 y
b1100 <
b1000 E
b1000 O
b111 Y
b111 c
b1110 D
b1110 N
b111 X
b111 b
b101 l
b101 v
b1111011110001100 $
b1111011110001100 )
b101011111101101 #
b101011111101101 (
b100 ""
b11011111010000100 &
#80000
0"
02
01
b1001 ,
b1001 e
b1011 *
b1011 y
b1000 -
b1000 [
b1010 +
b1010 o
06
b11000 H
b11001 R
b1001 f
b1 z
b1000 /
b1000 G
b1001 .
b1001 Q
b1000 \
b0 p
b1010100110001011 !
b1010100110001011 0
b1011 =
b101 <
b1100 E
b1100 O
b100 Y
b100 c
b1000 m
b1000 w
b110 ;
b1100 D
b1100 N
b100 X
b100 b
b10 l
b10 v
b1000 >
0%
b1000010011000101 $
b1000010011000101 )
b10010011000110 #
b10010011000110 (
b101 ""
b10100111101111010 &
#90000
1"
12
11
b11100 H
b101 /
b101 G
b11111 R
b110 .
b110 Q
b1100 \
b110 +
b110 o
b11110 p
b111 *
b111 y
b110101001011100 !
b110101001011100 0
b1100 =
b1110 >
b1001 -
b1001 [
b1010 ,
b1010 e
b1111 f
b11111 z
b111 <
b111 E
b111 O
b10 Y
b10 c
b111 m
b111 w
b101 ;
b1110 D
b1110 N
b111 X
b111 b
b1111 l
b1111 v
b111001001110111 $
b111001001110111 )
b1111011111100101 #
b1111011111100101 (
b110 ""
b1010100110001011 &
#100000
19
16
18
17
b11000 p
b100010110000001 !
b100010110000001 0
b1 =
b11100 >
b10000 H
b111 /
b111 G
b1000 .
b1000 Q
b100 -
b100 [
b10110 \
b101 ,
b101 e
b10111 f
b11 +
b11 o
b100 *
b100 y
b10 <
b1111 E
b1111 O
b1001 Y
b1001 c
b110 m
b110 w
b1111 ;
b1000 D
b1000 N
b1011 X
b1011 b
b1101 l
b1101 v
b110100111110010 $
b110100111110010 )
b1101101110001111 #
b1101101110001111 (
b111 ""
b10110101001011100 &
#110000
06
0"
02
01
b11001 R
b1000 -
b1000 [
b1001 ,
b1001 e
b11101 f
b1010 /
b1010 G
b11000 H
b1011 .
b1011 Q
b11100 \
b1011 +
b1011 o
b1000 p
b1100 *
b1100 y
b1111 z
b1100100110101110 !
b1100100110101110 0
b1110 =
b101 <
b1100 E
b1100 O
b1110 Y
b1110 c
b100 m
b100 w
b1000 ;
b1110 D
b1110 N
b1010 X
b1010 b
b111 l
b111 v
b11 >
1%
b100111011000101 $
b100111011000101 )
b111101011101000 #
b111101011101000 (
b1000 ""
b10100010110000001 &
#120000
05
04
03
16
b0 -
b0 [
b1 ,
b1 e
b1000000011101010 !
b1000000011101010 0
b1010 =
b1101 /
b1101 G
b100 H
b1110 .
b1110 Q
b111 R
b10000 \
b10001 f
b111 +
b111 o
b0 p
b1000 *
b1000 y
b1101 <
b10 E
b10 O
b1000 Y
b1000 c
b101 m
b101 w
b1101 ;
b1011 D
b1011 N
b1000 X
b1000 b
b10 l
b10 v
b11010 >
0%
b101100000101101 $
b101100000101101 )
b10100010111101 #
b10100010111101 (
b1001 ""
b1100100110101110 &
#130000
06
09
01
08
07
b1001 -
b1001 [
b1010 ,
b1010 e
b1110 +
b1110 o
b1111 *
b1111 y
b1 z
b100 >
b1110100101101101 !
b1110100101101101 0
b1101 =
b0 H
b110 /
b110 G
b1 R
b111 .
b111 Q
b1100 \
b1111 f
b1010 <
b0 E
b0 O
b111 Y
b111 c
b1000 m
b1000 w
b11 ;
b110 D
b110 N
b10 X
b10 b
b110 l
b110 v
b1000011100001010 $
b1000011100001010 )
b110001001100011 #
b110001001100011 (
b1010 ""
b1000000011101010 &
#140000
b100 H
b101 R
b11 f
b110 +
b110 o
b111 *
b111 y
b110011011001010 !
b110011011001010 0
b1010 =
b0 >
b1100 /
b1100 G
b1101 .
b1101 Q
b110 -
b110 [
b10 \
b111 ,
b111 e
b1010 E
b1010 O
b101 Y
b101 c
b100 m
b100 w
b0 ;
b10 D
b10 N
b1 X
b1 b
b10 l
b10 v
b100010110101010 $
b100010110101010 )
b10000100100000 #
b10000100100000 (
b1011 ""
b1110100101101101 &
#150000
19
b1010 /
b1010 G
b1011 .
b1011 Q
18
17
b110 p
b1110 +
b1110 o
b1111 *
b1111 y
b1100 >
b1111011010101001 !
b1111011010101001 0
b1001 =
b10 H
b11 R
b110 -
b110 [
b10000 \
b111 ,
b111 e
b10001 f
b111 z
b11 <
b1 E
b1 O
b1000 Y
b1000 c
b1011 m
b1011 w
b110 ;
b1001 D
b1001 N
b1110 X
b1110 b
b11 l
b11 v
b1011100000010011 $
b1011100000010011 )
b11111010010110 #
b11111010010110 (
b1100 ""
b110011011001010 &
#160000
19
1"
06
18
17
12
11
b1000 H
b1111 R
b1011001110111110 !
b1011001110111110 0
b1110 =
b110 >
b1011 /
b1011 G
b1100 .
b1100 Q
b11 -
b11 [
b11000 \
b100 ,
b100 e
b11111 f
b1010 +
b1010 o
b11010 p
b1011 *
b1011 y
b11011 z
b1011 <
b110 E
b110 O
b1101 Y
b1101 c
b1101 m
b1101 w
b11 ;
b101 D
b101 N
b110 X
b110 b
b1101 l
b1101 v
b1101110101101011 $
b1101110101101011 )
b1101011001010011 #
b1101011001010011 (
b1101 ""
b1111011010101001 &
#170000
16
05
0"
04
03
02
01
b11101 f
b1111 z
b1010 /
b1010 G
b0 H
b1011 .
b1011 Q
b1 R
b11100 \
b1000 -
b1000 [
b1001 ,
b1001 e
b111 +
b111 o
b0 p
b1000 *
b1000 y
b1000100010110001 !
b1000100010110001 0
b1 =
b1110 <
b1010 E
b1010 O
b1110 Y
b1110 c
b11 m
b11 w
b10 ;
b0 D
b0 N
b1010 X
b1010 b
b100 l
b100 v
b11101 >
1%
b11111010101110 $
b11111010101110 )
b100101000000010 #
b100101000000010 (
b1110 ""
b11011001110111110 &
#180000
09
08
07
b11 =
b1011101111110011 !
b1011101111110011 0
b0 \
b111 f
b1011 +
b1011 o
b1000 p
b1100 *
b1100 y
b11111 >
b1110 /
b1110 G
b1111 .
b1111 Q
b1011 -
b1011 [
b1100 ,
b1100 e
b11 <
b10 E
b10 O
b1001 Y
b1001 c
b100 m
b100 w
b1111 ;
b1100 D
b1100 N
b10 X
b10 b
b111 l
b111 v
b100100100100011 $
b100100100100011 )
b111001011001111 #
b111001011001111 (
b1111 ""
b1000100010110001 &
#190000
15
13
19
18
17
b10001 >
b101011100000111 !
b101011100000111 0
b111 =
b1111 /
b1111 G
b0 .
b0 Q
b11111 R
b110 -
b110 [
b10000 \
b111 ,
b111 e
b10001 f
b100 +
b100 o
b0 p
b1 z
b101 *
b101 y
b1100 <
b11 E
b11 O
b1100 Y
b1100 c
b1010 ;
b1010 X
b1010 b
b0 l
b0 v
b100110000111100 $
b100110000111100 )
b101011001010 #
b101011001010 (
b10000 ""
b1011101111110011 &
#200000
1"
03
12
11
05
09
06
08
07
b1010011001011 !
b1010011001011 0
b1011 =
b1100 /
b1100 G
b1101 .
b1101 Q
b1 R
b100 -
b100 [
b101 ,
b101 e
b11100 p
b1 +
b1 o
b11111 z
b10 *
b10 y
b110 \
b111 f
b1 <
b100 E
b100 O
b11 Y
b11 c
b1011 m
b1011 w
b1000 D
b1000 N
b1 X
b1 b
b110 l
b110 v
b0 >
0%
b1011001101000001 $
b1011001101000001 )
b110000110001010 #
b110000110001010 (
b10001 ""
b101011100000111 &
#210000
15
13
1"
12
16
b100 \
b1111 /
b1111 G
b11111 R
b0 .
b0 Q
b101 -
b101 [
b110 ,
b110 e
b0 +
b0 o
b11110 p
b1 *
b1 y
b11000000010 !
b11000000010 0
b10 =
b1001 <
b1000 E
b1000 O
b10 Y
b10 c
b1 m
b1 w
b1000 ;
b111 D
b111 N
b11 X
b11 b
b1111 l
b1111 v
b10011 >
1%
b1001010001001 $
b1001010001001 )
b1111001101111000 #
b1111001101111000 (
b10010 ""
b10001010011001011 &
#220000
09
08
07
06
14
b101111101111101 !
b101111101111101 0
b1101 =
b1101 >
b111 /
b111 G
b10000 H
b1000 .
b1000 Q
b1110 -
b1110 [
b10 \
b1111 ,
b1111 e
b11 f
b101 +
b101 o
b11100 p
b110 *
b110 y
b110 <
b1100 E
b1100 O
b1001 Y
b1001 c
b1111 m
b1111 w
b110 ;
b1011 D
b1011 N
b101 X
b101 b
b110 l
b110 v
b1111100111000110 $
b1111100111000110 )
b110010110110110 #
b110010110110110 (
b10011 ""
b10000011000000010 &
#230000
0"
09
01
08
17
02
05
03
04
16
b1101 /
b1101 G
b100 H
b111 R
b1110 .
b1110 Q
b11 z
b1111 -
b1111 [
b0 \
b0 ,
b0 e
b11111 f
b0 p
b1101 +
b1101 o
b1110 *
b1110 y
b1101111111100110 !
b1101111111100110 0
b110 =
b1010 <
b10 E
b10 O
b1101 Y
b1101 c
b1101 m
b1101 w
b1100 ;
b10 X
b10 b
b0 l
b0 v
b10000 >
0%
b1101110100101010 $
b1101110100101010 )
b1010111100 #
b1010111100 (
b10100 ""
b10101111101111101 &
#240000
0"
09
11
05
04
13
06
b1111 /
b1111 G
b0 H
b0 .
b0 Q
b11111 R
b1111 +
b1111 o
b0 *
b0 y
b11111 z
b1111111111110111 !
b1111111111110111 0
b111 =
b101 <
b1000 E
b1000 O
b1 Y
b1 c
b100 m
b100 w
b1 ;
b111 D
b111 N
b1110 X
b1110 b
b1011 l
b1011 v
b11 >
1%
b100000110000101 $
b100000110000101 )
b1011111001110001 #
b1011111001110001 (
b10101 ""
b1101111111100110 &
#250000
16
03
07
01
b1001001101110101 !
b1001001101110101 0
b101 =
b110 H
b1100 p
b110 /
b110 G
b111 .
b111 Q
b111 R
b11 -
b11 [
b100 ,
b100 e
b111 f
b1001 +
b1001 o
b1010 *
b1010 y
b1111 z
b1010 <
b11 E
b11 O
b11 Y
b11 c
b11 m
b11 w
b1011 ;
b11 D
b11 N
b0 X
b0 b
b110 l
b110 v
b10100 >
0%
b11001100111010 $
b11001100111010 )
b110000000111011 #
b110000000111011 (
b10110 ""
b1111111111110111 &
#260000
15
14
13
19
0"
18
17
02
01
06
b11110 H
b11111 R
b10111 f
b1101 +
b1101 o
b1110 *
b1110 y
b11 z
b1110011100000111 !
b1110011100000111 0
b111 =
b0 /
b0 G
b1 .
b1 Q
b110 -
b110 [
b10110 \
b111 ,
b111 e
b0 p
b1 <
b1111 E
b1111 O
b1011 Y
b1011 c
b1001 m
b1001 w
b101 ;
b1 D
b1 N
b1011 X
b1011 b
b100 l
b100 v
b11 >
1%
b1001101111110001 $
b1001101111110001 )
b100101100010101 #
b100101100010101 (
b10111 ""
b1001001101110101 &
#270000
1"
11
06
05
19
04
03
18
17
b1001 R
b1111 +
b1111 o
b0 *
b0 y
b11111 z
b1010101111 !
b1010101111 0
b1111 =
b1 >
b1000 H
b1010 /
b1010 G
b1011 .
b1011 Q
b10 -
b10 [
b11110 \
b11 ,
b11 e
b11111 f
b1100 <
b100 E
b100 O
b1111 m
b1111 w
b10 ;
b110 D
b110 N
b111 X
b111 b
b0 l
b0 v
b1111101101001100 $
b1111101101001100 )
b11101100010 #
b11101100010 (
b11000 ""
b1110011100000111 &
#280000
09
08
07
15
16
14
13
12
b10101 z
b100101110000111 !
b100101110000111 0
b111 =
b111 /
b111 G
b10000 H
b1000 .
b1000 Q
b11111 R
b1010 -
b1010 [
b10 \
b1011 ,
b1011 e
b11 f
b100 +
b100 o
b10100 p
b101 *
b101 y
b1000 <
b1111 E
b1111 O
b1001 Y
b1001 c
b1010 m
b1010 w
b1111 ;
b1000 D
b1000 N
b1 X
b1 b
b1010 l
b1010 v
b10000 >
0%
b1010100111111000 $
b1010100111111000 )
b1010000110001111 #
b1010000110001111 (
b11001 ""
b10000001010101111 &
#290000
05
03
0"
04
02
01
b1110101011111011 !
b1110101011111011 0
b1011 =
b11000 >
b11 R
b1110 /
b1110 G
b10 H
b1111 .
b1111 Q
b1010 -
b1010 [
b1000 \
b1011 ,
b1011 e
b1001 f
b1110 +
b1110 o
b10 p
b1111 *
b1111 y
b11 z
b1100 <
b101 E
b101 O
b100 Y
b100 c
b1001 m
b1001 w
b1001 D
b1001 N
b110 X
b110 b
b101 l
b101 v
b1001010001011100 $
b1001010001011100 )
b101011010011111 #
b101011010011111 (
b11010 ""
b10100101110000111 &
#300000
b1101 .
b1101 Q
b1100 /
b1100 G
b1 R
b1100 \
b110100111010010 !
b110100111010010 0
b10 =
b10010 >
b0 H
b1001 -
b1001 [
b1010 ,
b1010 e
b1111 f
b110 p
b110 +
b110 o
b111 z
b111 *
b111 y
b1001 <
b100 E
b100 O
b10 Y
b10 c
b11 m
b11 w
b1001 ;
b1000 D
b1000 N
b111 X
b111 b
b11 l
b11 v
b11001001001001 $
b11001001001001 )
b11011110001001 #
b11011110001001 (
b11011 ""
b1110101011111011 &
#310000
15
14
13
09
1"
08
07
12
11
06
b10 /
b10 G
b11010 H
b11 .
b11 Q
b11011 R
b1100 -
b1100 [
b0 \
b1101 ,
b1101 e
b1 f
b1011 +
b1011 o
b11000 p
b1100 *
b1100 y
b11111 z
b1011110100101001 !
b1011110100101001 0
b1001 =
b1 <
b101 E
b101 O
b1100 Y
b1100 c
b1111 m
b1111 w
b111 ;
b1101 D
b1101 N
b0 X
b0 b
b1100 l
b1100 v
b1111 >
1%
b1111110001010001 $
b1111110001010001 )
b1100000011010111 #
b1100000011010111 (
b11100 ""
b110100111010010 &
#320000
05
04
03
19
06
18
17
b100110111001111 !
b100110111001111 0
b1111 =
b1 >
b1100 /
b1100 G
b0 H
b1101 .
b1101 Q
b1 R
b1101 -
b1101 [
b11100 \
b1110 ,
b1110 e
b11111 f
b11 +
b11 o
b100 *
b100 y
b10 <
b1100 E
b1100 O
b1110 Y
b1110 c
b1100 m
b1100 w
b1100 ;
b0 D
b0 N
b1111 X
b1111 b
b111 l
b111 v
b1100111011000010 $
b1100111011000010 )
b111111100001100 #
b111111100001100 (
b11101 ""
b11011110100101001 &
#330000
16
b100011110110101 !
b100011110110101 0
b101 =
b1110 H
b1010 /
b1010 G
b1011 .
b1011 Q
b10000 \
b11111 >
b1111 R
b111 -
b111 [
b1000 ,
b1000 e
b1101 <
b11 E
b11 O
b1101 Y
b1101 c
b1110 m
b1110 w
b111 ;
b111 D
b111 N
b1010 X
b1010 b
b101 l
b101 v
b1110110100111101 $
b1110110100111101 )
b101101001110111 #
b101101001110111 (
b11110 ""
b10100110111001111 &
#340000
01
0"
02
09
07
08
b1100 H
b1101 /
b1101 G
b1110 .
b1110 Q
b1000000111101100 !
b1000000111101100 0
b1100 =
b1 -
b1 [
b0 \
b10 ,
b10 e
b11 f
b1000 +
b1000 o
b0 p
b1001 *
b1001 y
b1 z
b110 E
b110 O
b1 Y
b1 c
b1000 m
b1000 w
b1110 ;
b0 X
b0 b
b0 l
b0 v
b1000000101101101 $
b1000000101101101 )
b1111110 #
b1111110 (
b11111 ""
b10100011110110101 &
#350000
19
18
17
05
1"
04
03
12
11
b11 R
b11100 \
b1000010111110011 !
b1000010111110011 0
b11 =
b10 H
b1110 /
b1110 G
b1111 .
b1111 Q
b101 -
b101 [
b11111 f
b110 ,
b110 e
b111 +
b111 o
b10000 p
b1000 *
b1000 y
b11111 z
b11 <
b1101 E
b1101 O
b110 Y
b110 c
b1111 m
b1111 w
b1111 ;
b1 D
b1 N
b1111 X
b1111 b
b1000 l
b1000 v
b1111011011010011 $
b1111011011010011 )
b1000111100011111 #
b1000111100011111 (
b100000 ""
b1000000111101100 &
#360000
0"
01
02
b1 -
b1 [
b10011 f
b10 ,
b10 e
b1101 +
b1101 o
b0 p
b11 z
b1110 *
b1110 y
b1110000111010100 !
b1110000111010100 0
b100 =
b10111 >
b1100 /
b1100 G
b1110 H
b1101 .
b1101 Q
b1111 R
b10000 \
b1011 <
b101 E
b101 O
b1001 Y
b1001 c
b101 m
b101 w
b1000 ;
b111 D
b111 N
b1000 X
b1000 b
b101100101011011 $
b101100101011011 )
b1000100001111000 #
b1000100001111000 (
b100001 ""
b11000010111110011 &
#370000
b1101 -
b1101 [
1"
b1110 ,
b1110 e
12
11
b101 /
b101 G
b100 H
b110 .
b110 Q
b111 R
b11100 \
b100 +
b100 o
b10100 p
b101 *
b101 y
b101110101101010 !
b101110101101010 0
b1010 =
b11111 >
b11111 f
b10101 z
b1010 <
b10 E
b10 O
b1111 Y
b1111 c
b1010 m
b1010 w
b1111 ;
b11 D
b11 N
b1110 X
b1110 b
b1010 l
b1010 v
b1010111100101010 $
b1010111100101010 )
b1010111000111111 #
b1010111000111111 (
b100010 ""
b1110000111010100 &
